[{"matchId":"980901","innings":1,"wicket":1,"batter1":"LMP Simmons","batter2":"RG Sharma","runs":8,"balls":7},{"matchId":"980901","innings":1,"wicket":2,"batter1":"LMP Simmons","batter2":"HH Pandya","runs":21,"balls":16},{"matchId":"980901","innings":1,"wicket":3,"batter1":"JC Buttler","batter2":"HH Pandya","runs":0,"balls":2},{"matchId":"980901","innings":1,"wicket":4,"batter1":"JC Buttler","batter2":"AT Rayudu","runs":1,"balls":5},{"matchId":"980901","innings":1,"wicket":5,"batter1":"AT Rayudu","batter2":"AT Rayudu","runs":10,"balls":13},{"matchId":"980901","innings":1,"wicket":6,"batter1":"AT Rayudu","batter2":"S Gopal","runs":11,"balls":23},{"matchId":"980901","innings":1,"wicket":7,"batter1":"AT Rayudu","batter2":"Harbhajan Singh","runs":17,"balls":25},{"matchId":"980901","innings":1,"wicket":8,"batter1":"R Vinay Kumar","batter2":"Harbhajan Singh","runs":28,"balls":21},{"matchId":"980901","innings":1,"wicket":9,"batter1":"Harbhajan Singh","batter2":"Harbhajan Singh","runs":25,"balls":8},{"matchId":"980901","innings":2,"wicket":1,"batter1":"AM Rahane","batter2":"F du Plessis","runs":78,"balls":59},{"matchId":"980901","innings":2,"wicket":2,"batter1":"AM Rahane","batter2":"KP Pietersen","runs":48,"balls":30},{"matchId":"980903","innings":1,"wicket":1,"batter1":"MA Agarwal","batter2":"Q de Kock","runs":24,"balls":14},{"matchId":"980903","innings":1,"wicket":2,"batter1":"MA Agarwal","batter2":"SS Iyer","runs":1,"balls":4},{"matchId":"980903","innings":1,"wicket":3,"batter1":"MA Agarwal","batter2":"KK Nair","runs":6,"balls":11},{"matchId":"980903","innings":1,"wicket":4,"batter1":"SV Samson","batter2":"KK Nair","runs":4,"balls":4},{"matchId":"980903","innings":1,"wicket":5,"batter1":"SV Samson","batter2":"P Negi","runs":20,"balls":27},{"matchId":"980903","innings":1,"wicket":6,"batter1":"SV Samson","batter2":"CR Brathwaite","runs":12,"balls":5},{"matchId":"980903","innings":1,"wicket":7,"batter1":"SV Samson","batter2":"CH Morris","runs":17,"balls":11},{"matchId":"980903","innings":1,"wicket":8,"batter1":"SV Samson","batter2":"NM Coulter-Nile","runs":0,"balls":3},{"matchId":"980903","innings":1,"wicket":9,"batter1":"A Mishra","batter2":"NM Coulter-Nile","runs":8,"balls":15},{"matchId":"980903","innings":1,"wicket":10,"batter1":"Z Khan","batter2":"NM Coulter-Nile","runs":6,"balls":12},{"matchId":"980903","innings":2,"wicket":1,"batter1":"RV Uthappa","batter2":"G Gambhir","runs":69,"balls":59},{"matchId":"980903","innings":2,"wicket":2,"batter1":"MK Pandey","batter2":"G Gambhir","runs":30,"balls":27},{"matchId":"980905","innings":1,"wicket":1,"batter1":"M Vijay","batter2":"M Vohra","runs":78,"balls":50},{"matchId":"980905","innings":1,"wicket":2,"batter1":"M Vijay","batter2":"DA Miller","runs":13,"balls":14},{"matchId":"980905","innings":1,"wicket":3,"batter1":"GJ Maxwell","batter2":"DA Miller","runs":10,"balls":6},{"matchId":"980905","innings":1,"wicket":4,"batter1":"WP Saha","batter2":"DA Miller","runs":1,"balls":2},{"matchId":"980905","innings":1,"wicket":5,"batter1":"WP Saha","batter2":"MP Stoinis","runs":55,"balls":45},{"matchId":"980905","innings":1,"wicket":6,"batter1":"MP Stoinis","batter2":"MP Stoinis","runs":0,"balls":1},{"matchId":"980905","innings":1,"wicket":7,"batter1":"AR Patel","batter2":"MP Stoinis","runs":4,"balls":2},{"matchId":"980905","innings":2,"wicket":1,"batter1":"AJ Finch","batter2":"BB McCullum","runs":1,"balls":6},{"matchId":"980905","innings":2,"wicket":2,"batter1":"AJ Finch","batter2":"SK Raina","runs":51,"balls":27},{"matchId":"980905","innings":2,"wicket":3,"batter1":"AJ Finch","batter2":"KD Karthik","runs":65,"balls":38},{"matchId":"980905","innings":2,"wicket":4,"batter1":"RA Jadeja","batter2":"KD Karthik","runs":16,"balls":16},{"matchId":"980905","innings":2,"wicket":5,"batter1":"Ishan Kishan","batter2":"KD Karthik","runs":18,"balls":14},{"matchId":"980905","innings":2,"wicket":6,"batter1":"KD Karthik","batter2":"KD Karthik","runs":11,"balls":5},{"matchId":"980907","innings":1,"wicket":1,"batter1":"CH Gayle","batter2":"V Kohli","runs":6,"balls":8},{"matchId":"980907","innings":1,"wicket":2,"batter1":"AB de Villiers","batter2":"V Kohli","runs":157,"balls":87},{"matchId":"980907","innings":1,"wicket":3,"batter1":"AB de Villiers","batter2":"SR Watson","runs":20,"balls":9},{"matchId":"980907","innings":1,"wicket":4,"batter1":"SR Watson","batter2":"SR Watson","runs":0,"balls":1},{"matchId":"980907","innings":1,"wicket":5,"batter1":"KM Jadhav","batter2":"SR Watson","runs":44,"balls":16},{"matchId":"980907","innings":2,"wicket":1,"batter1":"DA Warner","batter2":"S Dhawan","runs":35,"balls":19},{"matchId":"980907","innings":2,"wicket":2,"batter1":"DA Warner","batter2":"MC Henriques","runs":51,"balls":33},{"matchId":"980907","innings":2,"wicket":3,"batter1":"NV Ojha","batter2":"MC Henriques","runs":2,"balls":5},{"matchId":"980907","innings":2,"wicket":4,"batter1":"MC Henriques","batter2":"MC Henriques","runs":5,"balls":6},{"matchId":"980907","innings":2,"wicket":5,"batter1":"DJ Hooda","batter2":"MC Henriques","runs":8,"balls":6},{"matchId":"980907","innings":2,"wicket":6,"batter1":"A Ashish Reddy","batter2":"MC Henriques","runs":46,"balls":27},{"matchId":"980907","innings":2,"wicket":7,"batter1":"EJG Morgan","batter2":"MC Henriques","runs":35,"balls":24},{"matchId":"980909","innings":1,"wicket":1,"batter1":"RV Uthappa","batter2":"G Gambhir","runs":21,"balls":22},{"matchId":"980909","innings":1,"wicket":2,"batter1":"G Gambhir","batter2":"G Gambhir","runs":100,"balls":60},{"matchId":"980909","innings":1,"wicket":3,"batter1":"G Gambhir","batter2":"AD Russell","runs":43,"balls":22},{"matchId":"980909","innings":1,"wicket":4,"batter1":"G Gambhir","batter2":"YK Pathan","runs":6,"balls":5},{"matchId":"980909","innings":1,"wicket":5,"batter1":"YK Pathan","batter2":"YK Pathan","runs":13,"balls":10},{"matchId":"980909","innings":1,"wicket":6,"batter1":"YK Pathan","batter2":"SA Yadav","runs":4,"balls":1},{"matchId":"980909","innings":2,"wicket":1,"batter1":"RG Sharma","batter2":"PA Patel","runs":53,"balls":35},{"matchId":"980909","innings":2,"wicket":2,"batter1":"RG Sharma","batter2":"HH Pandya","runs":34,"balls":26},{"matchId":"980909","innings":2,"wicket":3,"batter1":"RG Sharma","batter2":"MJ McClenaghan","runs":22,"balls":10},{"matchId":"980909","innings":2,"wicket":4,"batter1":"RG Sharma","batter2":"JC Buttler","runs":66,"balls":40},{"matchId":"980909","innings":2,"wicket":5,"batter1":"RG Sharma","batter2":"KA Pollard","runs":13,"balls":4},{"matchId":"980911","innings":1,"wicket":1,"batter1":"AM Rahane","batter2":"F du Plessis","runs":27,"balls":23},{"matchId":"980911","innings":1,"wicket":2,"batter1":"KP Pietersen","batter2":"F du Plessis","runs":86,"balls":61},{"matchId":"980911","innings":1,"wicket":3,"batter1":"F du Plessis","batter2":"F du Plessis","runs":19,"balls":10},{"matchId":"980911","innings":1,"wicket":4,"batter1":"MS Dhoni","batter2":"F du Plessis","runs":2,"balls":4},{"matchId":"980911","innings":1,"wicket":5,"batter1":"MS Dhoni","batter2":"MR Marsh","runs":9,"balls":14},{"matchId":"980911","innings":1,"wicket":6,"batter1":"MS Dhoni","batter2":"R Bhatia","runs":20,"balls":8},{"matchId":"980911","innings":2,"wicket":1,"batter1":"AJ Finch","batter2":"BB McCullum","runs":85,"balls":51},{"matchId":"980911","innings":2,"wicket":2,"batter1":"SK Raina","batter2":"BB McCullum","runs":35,"balls":28},{"matchId":"980911","innings":2,"wicket":3,"batter1":"SK Raina","batter2":"DJ Bravo","runs":27,"balls":18},{"matchId":"980911","innings":2,"wicket":4,"batter1":"RA Jadeja","batter2":"DJ Bravo","runs":17,"balls":12},{"matchId":"980913","innings":1,"wicket":1,"batter1":"M Vijay","batter2":"M Vohra","runs":8,"balls":9},{"matchId":"980913","innings":1,"wicket":2,"batter1":"SE Marsh","batter2":"M Vohra","runs":29,"balls":28},{"matchId":"980913","innings":1,"wicket":3,"batter1":"DA Miller","batter2":"M Vohra","runs":15,"balls":12},{"matchId":"980913","innings":1,"wicket":4,"batter1":"GJ Maxwell","batter2":"M Vohra","runs":0,"balls":3},{"matchId":"980913","innings":1,"wicket":5,"batter1":"M Vohra","batter2":"M Vohra","runs":7,"balls":12},{"matchId":"980913","innings":1,"wicket":6,"batter1":"WP Saha","batter2":"M Vohra","runs":6,"balls":14},{"matchId":"980913","innings":1,"wicket":7,"batter1":"AR Patel","batter2":"M Vohra","runs":8,"balls":13},{"matchId":"980913","innings":1,"wicket":8,"batter1":"MM Sharma","batter2":"M Vohra","runs":17,"balls":12},{"matchId":"980913","innings":1,"wicket":9,"batter1":"MG Johnson","batter2":"M Vohra","runs":9,"balls":10},{"matchId":"980913","innings":1,"wicket":10,"batter1":"Sandeep Sharma","batter2":"M Vohra","runs":12,"balls":7},{"matchId":"980913","innings":2,"wicket":1,"batter1":"Q de Kock","batter2":"SS Iyer","runs":9,"balls":13},{"matchId":"980913","innings":2,"wicket":2,"batter1":"Q de Kock","batter2":"SV Samson","runs":91,"balls":64},{"matchId":"980913","innings":2,"wicket":3,"batter1":"Q de Kock","batter2":"P Negi","runs":13,"balls":4},{"matchId":"980915","innings":1,"wicket":1,"batter1":"DA Warner","batter2":"S Dhawan","runs":18,"balls":17},{"matchId":"980915","innings":1,"wicket":2,"batter1":"DA Warner","batter2":"MC Henriques","runs":5,"balls":4},{"matchId":"980915","innings":1,"wicket":3,"batter1":"EJG Morgan","batter2":"MC Henriques","runs":13,"balls":16},{"matchId":"980915","innings":1,"wicket":4,"batter1":"EJG Morgan","batter2":"DJ Hooda","runs":14,"balls":22},{"matchId":"980915","innings":1,"wicket":5,"batter1":"EJG Morgan","batter2":"NV Ojha","runs":67,"balls":47},{"matchId":"980915","innings":1,"wicket":6,"batter1":"EJG Morgan","batter2":"A Ashish Reddy","runs":11,"balls":7},{"matchId":"980915","innings":1,"wicket":7,"batter1":"A Ashish Reddy","batter2":"A Ashish Reddy","runs":13,"balls":7},{"matchId":"980915","innings":1,"wicket":8,"batter1":"B Kumar","batter2":"A Ashish Reddy","runs":1,"balls":1},{"matchId":"980915","innings":2,"wicket":1,"batter1":"RV Uthappa","batter2":"G Gambhir","runs":92,"balls":75},{"matchId":"980915","innings":2,"wicket":2,"batter1":"AD Russell","batter2":"G Gambhir","runs":5,"balls":7},{"matchId":"980915","innings":2,"wicket":3,"batter1":"MK Pandey","batter2":"G Gambhir","runs":49,"balls":28},{"matchId":"980917","innings":1,"wicket":1,"batter1":"RG Sharma","batter2":"PA Patel","runs":7,"balls":9},{"matchId":"980917","innings":1,"wicket":2,"batter1":"HH Pandya","batter2":"PA Patel","runs":12,"balls":12},{"matchId":"980917","innings":1,"wicket":3,"batter1":"JC Buttler","batter2":"PA Patel","runs":32,"balls":32},{"matchId":"980917","innings":1,"wicket":4,"batter1":"KA Pollard","batter2":"PA Patel","runs":8,"balls":8},{"matchId":"980917","innings":1,"wicket":5,"batter1":"PA Patel","batter2":"PA Patel","runs":18,"balls":17},{"matchId":"980917","innings":1,"wicket":6,"batter1":"AT Rayudu","batter2":"PA Patel","runs":11,"balls":17},{"matchId":"980917","innings":1,"wicket":7,"batter1":"AT Rayudu","batter2":"KH Pandya","runs":11,"balls":8},{"matchId":"980917","innings":1,"wicket":8,"batter1":"KH Pandya","batter2":"KH Pandya","runs":42,"balls":18},{"matchId":"980917","innings":1,"wicket":9,"batter1":"KH Pandya","batter2":"MJ McClenaghan","runs":2,"balls":1},{"matchId":"980917","innings":2,"wicket":1,"batter1":"AJ Finch","batter2":"BB McCullum","runs":12,"balls":9},{"matchId":"980917","innings":2,"wicket":2,"batter1":"AJ Finch","batter2":"SK Raina","runs":53,"balls":42},{"matchId":"980917","innings":2,"wicket":3,"batter1":"AJ Finch","batter2":"KD Karthik","runs":15,"balls":16},{"matchId":"980917","innings":2,"wicket":4,"batter1":"AJ Finch","batter2":"DJ Bravo","runs":3,"balls":7},{"matchId":"980917","innings":2,"wicket":5,"batter1":"AJ Finch","batter2":"AD Nath","runs":26,"balls":23},{"matchId":"980917","innings":2,"wicket":6,"batter1":"AJ Finch","batter2":"JP Faulkner","runs":22,"balls":14},{"matchId":"980917","innings":2,"wicket":7,"batter1":"AJ Finch","batter2":"P Kumar","runs":0,"balls":2},{"matchId":"980917","innings":2,"wicket":8,"batter1":"AJ Finch","batter2":"DS Kulkarni","runs":16,"balls":8},{"matchId":"980919","innings":1,"wicket":1,"batter1":"AM Rahane","batter2":"F du Plessis","runs":10,"balls":13},{"matchId":"980919","innings":1,"wicket":2,"batter1":"KP Pietersen","batter2":"F du Plessis","runs":55,"balls":35},{"matchId":"980919","innings":1,"wicket":3,"batter1":"F du Plessis","batter2":"F du Plessis","runs":11,"balls":13},{"matchId":"980919","innings":1,"wicket":4,"batter1":"F du Plessis","batter2":"SPD Smith","runs":63,"balls":46},{"matchId":"980919","innings":1,"wicket":5,"batter1":"F du Plessis","batter2":"MS Dhoni","runs":10,"balls":8},{"matchId":"980919","innings":1,"wicket":6,"batter1":"MS Dhoni","batter2":"MS Dhoni","runs":0,"balls":1},{"matchId":"980919","innings":1,"wicket":7,"batter1":"IK Pathan","batter2":"MS Dhoni","runs":3,"balls":4},{"matchId":"980919","innings":2,"wicket":1,"batter1":"M Vijay","batter2":"M Vohra","runs":97,"balls":74},{"matchId":"980919","innings":2,"wicket":2,"batter1":"M Vijay","batter2":"SE Marsh","runs":6,"balls":11},{"matchId":"980919","innings":2,"wicket":3,"batter1":"M Vijay","batter2":"DA Miller","runs":9,"balls":5},{"matchId":"980919","innings":2,"wicket":4,"batter1":"DA Miller","batter2":"DA Miller","runs":7,"balls":8},{"matchId":"980919","innings":2,"wicket":5,"batter1":"GJ Maxwell","batter2":"DA Miller","runs":34,"balls":14},{"matchId":"980921","innings":1,"wicket":1,"batter1":"CH Gayle","batter2":"V Kohli","runs":0,"balls":3},{"matchId":"980921","innings":1,"wicket":2,"batter1":"AB de Villiers","batter2":"V Kohli","runs":107,"balls":65},{"matchId":"980921","innings":1,"wicket":3,"batter1":"SR Watson","batter2":"V Kohli","runs":63,"balls":30},{"matchId":"980921","innings":1,"wicket":4,"batter1":"SN Khan","batter2":"V Kohli","runs":2,"balls":3},{"matchId":"980921","innings":1,"wicket":5,"batter1":"KM Jadhav","batter2":"V Kohli","runs":5,"balls":8},{"matchId":"980921","innings":1,"wicket":6,"batter1":"KM Jadhav","batter2":"D Wiese","runs":14,"balls":11},{"matchId":"980921","innings":2,"wicket":1,"batter1":"Q de Kock","batter2":"SS Iyer","runs":11,"balls":6},{"matchId":"980921","innings":2,"wicket":2,"batter1":"Q de Kock","batter2":"SV Samson","runs":39,"balls":28},{"matchId":"980921","innings":2,"wicket":3,"batter1":"Q de Kock","batter2":"KK Nair","runs":134,"balls":77},{"matchId":"980921","innings":2,"wicket":4,"batter1":"JP Duminy","batter2":"KK Nair","runs":8,"balls":5},{"matchId":"980923","innings":1,"wicket":1,"batter1":"MJ Guptill","batter2":"PA Patel","runs":2,"balls":4},{"matchId":"980923","innings":1,"wicket":2,"batter1":"AT Rayudu","batter2":"PA Patel","runs":21,"balls":20},{"matchId":"980923","innings":1,"wicket":3,"batter1":"AT Rayudu","batter2":"RG Sharma","runs":20,"balls":19},{"matchId":"980923","innings":1,"wicket":4,"batter1":"AT Rayudu","batter2":"JC Buttler","runs":17,"balls":21},{"matchId":"980923","innings":1,"wicket":5,"batter1":"AT Rayudu","batter2":"KH Pandya","runs":63,"balls":39},{"matchId":"980923","innings":1,"wicket":6,"batter1":"HH Pandya","batter2":"KH Pandya","runs":12,"balls":10},{"matchId":"980923","innings":1,"wicket":7,"batter1":"Harbhajan Singh","batter2":"KH Pandya","runs":7,"balls":7},{"matchId":"980923","innings":2,"wicket":1,"batter1":"DA Warner","batter2":"S Dhawan","runs":4,"balls":5},{"matchId":"980923","innings":2,"wicket":2,"batter1":"DA Warner","batter2":"MC Henriques","runs":62,"balls":57},{"matchId":"980923","innings":2,"wicket":3,"batter1":"DA Warner","batter2":"EJG Morgan","runs":34,"balls":25},{"matchId":"980923","innings":2,"wicket":4,"batter1":"DA Warner","batter2":"DJ Hooda","runs":45,"balls":19},{"matchId":"980925","innings":1,"wicket":1,"batter1":"M Vijay","batter2":"M Vohra","runs":21,"balls":22},{"matchId":"980925","innings":1,"wicket":2,"batter1":"M Vijay","batter2":"SE Marsh","runs":26,"balls":25},{"matchId":"980925","innings":1,"wicket":3,"batter1":"WP Saha","batter2":"SE Marsh","runs":12,"balls":17},{"matchId":"980925","innings":1,"wicket":4,"batter1":"DA Miller","batter2":"SE Marsh","runs":13,"balls":9},{"matchId":"980925","innings":1,"wicket":5,"batter1":"GJ Maxwell","batter2":"SE Marsh","runs":22,"balls":16},{"matchId":"980925","innings":1,"wicket":6,"batter1":"AR Patel","batter2":"SE Marsh","runs":14,"balls":13},{"matchId":"980925","innings":1,"wicket":7,"batter1":"SE Marsh","batter2":"SE Marsh","runs":7,"balls":6},{"matchId":"980925","innings":1,"wicket":8,"batter1":"SE Marsh","batter2":"P Sahu","runs":3,"balls":3},{"matchId":"980925","innings":1,"wicket":9,"batter1":"SE Marsh","batter2":"KJ Abbott","runs":20,"balls":9},{"matchId":"980925","innings":2,"wicket":1,"batter1":"RV Uthappa","batter2":"G Gambhir","runs":82,"balls":51},{"matchId":"980925","innings":2,"wicket":2,"batter1":"MK Pandey","batter2":"G Gambhir","runs":15,"balls":14},{"matchId":"980925","innings":2,"wicket":3,"batter1":"MK Pandey","batter2":"Shakib Al Hasan","runs":13,"balls":14},{"matchId":"980925","innings":2,"wicket":4,"batter1":"SA Yadav","batter2":"Shakib Al Hasan","runs":13,"balls":16},{"matchId":"980925","innings":2,"wicket":5,"batter1":"SA Yadav","batter2":"YK Pathan","runs":18,"balls":8},{"matchId":"980927","innings":1,"wicket":1,"batter1":"V Kohli","batter2":"KL Rahul","runs":32,"balls":23},{"matchId":"980927","innings":1,"wicket":2,"batter1":"V Kohli","batter2":"AB de Villiers","runs":59,"balls":39},{"matchId":"980927","innings":1,"wicket":3,"batter1":"AB de Villiers","batter2":"AB de Villiers","runs":2,"balls":4},{"matchId":"980927","innings":1,"wicket":4,"batter1":"SR Watson","batter2":"AB de Villiers","runs":6,"balls":15},{"matchId":"980927","innings":1,"wicket":5,"batter1":"SN Khan","batter2":"AB de Villiers","runs":63,"balls":34},{"matchId":"980927","innings":1,"wicket":6,"batter1":"SN Khan","batter2":"STR Binny","runs":7,"balls":3},{"matchId":"980927","innings":1,"wicket":7,"batter1":"STR Binny","batter2":"STR Binny","runs":0,"balls":1},{"matchId":"980927","innings":1,"wicket":8,"batter1":"KW Richardson","batter2":"STR Binny","runs":1,"balls":1},{"matchId":"980927","innings":2,"wicket":1,"batter1":"RG Sharma","batter2":"PA Patel","runs":6,"balls":7},{"matchId":"980927","innings":2,"wicket":2,"batter1":"RG Sharma","batter2":"AT Rayudu","runs":76,"balls":56},{"matchId":"980927","innings":2,"wicket":3,"batter1":"RG Sharma","batter2":"JC Buttler","runs":27,"balls":16},{"matchId":"980927","innings":2,"wicket":4,"batter1":"KA Pollard","batter2":"JC Buttler","runs":31,"balls":16},{"matchId":"980927","innings":2,"wicket":5,"batter1":"KA Pollard","batter2":"HH Pandya","runs":31,"balls":14},{"matchId":"980929","innings":1,"wicket":1,"batter1":"AJ Finch","batter2":"BB McCullum","runs":0,"balls":4},{"matchId":"980929","innings":1,"wicket":2,"batter1":"SK Raina","batter2":"BB McCullum","runs":56,"balls":40},{"matchId":"980929","innings":1,"wicket":3,"batter1":"SK Raina","batter2":"KD Karthik","runs":18,"balls":16},{"matchId":"980929","innings":1,"wicket":4,"batter1":"SK Raina","batter2":"DJ Bravo","runs":17,"balls":19},{"matchId":"980929","innings":1,"wicket":5,"batter1":"SK Raina","batter2":"RA Jadeja","runs":26,"balls":22},{"matchId":"980929","innings":1,"wicket":6,"batter1":"SK Raina","batter2":"AD Nath","runs":16,"balls":15},{"matchId":"980929","innings":1,"wicket":7,"batter1":"AD Nath","batter2":"AD Nath","runs":0,"balls":1},{"matchId":"980929","innings":1,"wicket":8,"batter1":"DW Steyn","batter2":"AD Nath","runs":2,"balls":3},{"matchId":"980929","innings":2,"wicket":1,"batter1":"DA Warner","batter2":"S Dhawan","runs":137,"balls":89},{"matchId":"980931","innings":1,"wicket":1,"batter1":"V Kohli","batter2":"KL Rahul","runs":27,"balls":22},{"matchId":"980931","innings":1,"wicket":2,"batter1":"V Kohli","batter2":"AB de Villiers","runs":155,"balls":96},{"matchId":"980931","innings":1,"wicket":3,"batter1":"AB de Villiers","batter2":"AB de Villiers","runs":0,"balls":1},{"matchId":"980931","innings":1,"wicket":4,"batter1":"SR Watson","batter2":"AB de Villiers","runs":3,"balls":2},{"matchId":"980931","innings":2,"wicket":1,"batter1":"AM Rahane","batter2":"F du Plessis","runs":12,"balls":10},{"matchId":"980931","innings":2,"wicket":2,"batter1":"AM Rahane","batter2":"KP Pietersen","runs":0,"balls":1},{"matchId":"980931","innings":2,"wicket":3,"batter1":"AM Rahane","batter2":"SPD Smith","runs":6,"balls":4},{"matchId":"980931","innings":2,"wicket":4,"batter1":"AM Rahane","batter2":"MS Dhoni","runs":91,"balls":73},{"matchId":"980931","innings":2,"wicket":5,"batter1":"NLTC Perera","batter2":"MS Dhoni","runs":11,"balls":7},{"matchId":"980931","innings":2,"wicket":6,"batter1":"NLTC Perera","batter2":"R Bhatia","runs":44,"balls":16},{"matchId":"980931","innings":2,"wicket":7,"batter1":"R Bhatia","batter2":"R Bhatia","runs":1,"balls":2},{"matchId":"980931","innings":2,"wicket":8,"batter1":"R Bhatia","batter2":"Ankit Sharma","runs":4,"balls":4},{"matchId":"980931","innings":2,"wicket":9,"batter1":"M Ashwin","batter2":"Ankit Sharma","runs":0,"balls":1},{"matchId":"980931","innings":2,"wicket":10,"batter1":"Ankit Sharma","batter2":"Ankit Sharma","runs":3,"balls":2},{"matchId":"980933","innings":1,"wicket":1,"batter1":"Q de Kock","batter2":"SS Iyer","runs":11,"balls":12},{"matchId":"980933","innings":1,"wicket":2,"batter1":"SS Iyer","batter2":"SS Iyer","runs":37,"balls":30},{"matchId":"980933","innings":1,"wicket":3,"batter1":"KK Nair","batter2":"SS Iyer","runs":6,"balls":6},{"matchId":"980933","innings":1,"wicket":4,"batter1":"JP Duminy","batter2":"SS Iyer","runs":71,"balls":51},{"matchId":"980933","innings":1,"wicket":5,"batter1":"JP Duminy","batter2":"P Negi","runs":39,"balls":22},{"matchId":"980933","innings":2,"wicket":1,"batter1":"RG Sharma","batter2":"PA Patel","runs":9,"balls":10},{"matchId":"980933","innings":2,"wicket":2,"batter1":"RG Sharma","batter2":"AT Rayudu","runs":53,"balls":41},{"matchId":"980933","innings":2,"wicket":3,"batter1":"RG Sharma","batter2":"KH Pandya","runs":41,"balls":25},{"matchId":"980933","innings":2,"wicket":4,"batter1":"RG Sharma","batter2":"JC Buttler","runs":7,"balls":11},{"matchId":"980933","innings":2,"wicket":5,"batter1":"RG Sharma","batter2":"KA Pollard","runs":34,"balls":27},{"matchId":"980933","innings":2,"wicket":6,"batter1":"RG Sharma","batter2":"HH Pandya","runs":8,"balls":3},{"matchId":"980933","innings":2,"wicket":7,"batter1":"Harbhajan Singh","batter2":"HH Pandya","runs":0,"balls":1},{"matchId":"980933","innings":2,"wicket":8,"batter1":"TG Southee","batter2":"HH Pandya","runs":2,"balls":2},{"matchId":"980935","innings":1,"wicket":1,"batter1":"M Vijay","batter2":"M Vohra","runs":14,"balls":13},{"matchId":"980935","innings":1,"wicket":2,"batter1":"SE Marsh","batter2":"M Vohra","runs":21,"balls":22},{"matchId":"980935","innings":1,"wicket":3,"batter1":"SE Marsh","batter2":"DA Miller","runs":28,"balls":21},{"matchId":"980935","innings":1,"wicket":4,"batter1":"SE Marsh","batter2":"GJ Maxwell","runs":2,"balls":4},{"matchId":"980935","innings":1,"wicket":5,"batter1":"SE Marsh","batter2":"NS Naik","runs":24,"balls":21},{"matchId":"980935","innings":1,"wicket":6,"batter1":"AR Patel","batter2":"NS Naik","runs":50,"balls":35},{"matchId":"980935","innings":1,"wicket":7,"batter1":"AR Patel","batter2":"R Dhawan","runs":4,"balls":4},{"matchId":"980935","innings":2,"wicket":1,"batter1":"DA Warner","batter2":"S Dhawan","runs":90,"balls":59},{"matchId":"980935","innings":2,"wicket":2,"batter1":"AP Tare","batter2":"S Dhawan","runs":0,"balls":1},{"matchId":"980935","innings":2,"wicket":3,"batter1":"S Dhawan","batter2":"S Dhawan","runs":25,"balls":24},{"matchId":"980935","innings":2,"wicket":4,"batter1":"EJG Morgan","batter2":"S Dhawan","runs":24,"balls":17},{"matchId":"980935","innings":2,"wicket":5,"batter1":"MC Henriques","batter2":"S Dhawan","runs":0,"balls":1},{"matchId":"980935","innings":2,"wicket":6,"batter1":"MC Henriques","batter2":"NV Ojha","runs":7,"balls":5},{"matchId":"980937","innings":1,"wicket":1,"batter1":"V Kohli","batter2":"SR Watson","runs":8,"balls":10},{"matchId":"980937","innings":1,"wicket":2,"batter1":"V Kohli","batter2":"AB de Villiers","runs":51,"balls":36},{"matchId":"980937","innings":1,"wicket":3,"batter1":"V Kohli","batter2":"KL Rahul","runs":121,"balls":74},{"matchId":"980937","innings":2,"wicket":1,"batter1":"DR Smith","batter2":"BB McCullum","runs":47,"balls":33},{"matchId":"980937","innings":2,"wicket":2,"batter1":"BB McCullum","batter2":"BB McCullum","runs":40,"balls":18},{"matchId":"980937","innings":2,"wicket":3,"batter1":"KD Karthik","batter2":"BB McCullum","runs":53,"balls":44},{"matchId":"980937","innings":2,"wicket":4,"batter1":"KD Karthik","batter2":"RA Jadeja","runs":38,"balls":23},{"matchId":"980937","innings":2,"wicket":5,"batter1":"KD Karthik","batter2":"DJ Bravo","runs":4,"balls":1},{"matchId":"980939","innings":1,"wicket":1,"batter1":"AM Rahane","batter2":"F du Plessis","runs":24,"balls":24},{"matchId":"980939","innings":1,"wicket":2,"batter1":"AM Rahane","batter2":"SPD Smith","runs":56,"balls":50},{"matchId":"980939","innings":1,"wicket":3,"batter1":"AM Rahane","batter2":"NLTC Perera","runs":19,"balls":15},{"matchId":"980939","innings":1,"wicket":4,"batter1":"AM Rahane","batter2":"JA Morkel","runs":20,"balls":14},{"matchId":"980939","innings":1,"wicket":5,"batter1":"MS Dhoni","batter2":"JA Morkel","runs":14,"balls":6},{"matchId":"980939","innings":1,"wicket":6,"batter1":"MS Dhoni","batter2":"R Bhatia","runs":27,"balls":11},{"matchId":"980939","innings":2,"wicket":1,"batter1":"RV Uthappa","batter2":"G Gambhir","runs":0,"balls":1},{"matchId":"980939","innings":2,"wicket":2,"batter1":"SA Yadav","batter2":"G Gambhir","runs":31,"balls":16},{"matchId":"980939","innings":2,"wicket":3,"batter1":"SA Yadav","batter2":"Shakib Al Hasan","runs":29,"balls":22},{"matchId":"980939","innings":2,"wicket":4,"batter1":"SA Yadav","batter2":"YK Pathan","runs":51,"balls":47},{"matchId":"980939","innings":2,"wicket":5,"batter1":"SA Yadav","batter2":"AD Russell","runs":8,"balls":9},{"matchId":"980939","innings":2,"wicket":6,"batter1":"R Sathish","batter2":"AD Russell","runs":20,"balls":12},{"matchId":"980939","innings":2,"wicket":7,"batter1":"R Sathish","batter2":"PP Chawla","runs":12,"balls":5},{"matchId":"980939","innings":2,"wicket":8,"batter1":"UT Yadav","batter2":"PP Chawla","runs":5,"balls":4},{"matchId":"980939","innings":2,"wicket":9,"batter1":"UT Yadav","batter2":"SP Narine","runs":6,"balls":1},{"matchId":"980941","innings":1,"wicket":1,"batter1":"RG Sharma","batter2":"PA Patel","runs":0,"balls":2},{"matchId":"980941","innings":1,"wicket":2,"batter1":"AT Rayudu","batter2":"PA Patel","runs":137,"balls":86},{"matchId":"980941","innings":1,"wicket":3,"batter1":"PA Patel","batter2":"PA Patel","runs":37,"balls":20},{"matchId":"980941","innings":1,"wicket":4,"batter1":"PA Patel","batter2":"KA Pollard","runs":6,"balls":5},{"matchId":"980941","innings":1,"wicket":5,"batter1":"KA Pollard","batter2":"KA Pollard","runs":9,"balls":7},{"matchId":"980941","innings":1,"wicket":6,"batter1":"HH Pandya","batter2":"KA Pollard","runs":0,"balls":1},{"matchId":"980941","innings":2,"wicket":1,"batter1":"M Vijay","batter2":"M Vohra","runs":20,"balls":17},{"matchId":"980941","innings":2,"wicket":2,"batter1":"M Vohra","batter2":"M Vohra","runs":12,"balls":12},{"matchId":"980941","innings":2,"wicket":3,"batter1":"GJ Maxwell","batter2":"M Vohra","runs":89,"balls":61},{"matchId":"980941","innings":2,"wicket":4,"batter1":"GJ Maxwell","batter2":"DA Miller","runs":18,"balls":13},{"matchId":"980941","innings":2,"wicket":5,"batter1":"NS Naik","batter2":"DA Miller","runs":2,"balls":4},{"matchId":"980941","innings":2,"wicket":6,"batter1":"AR Patel","batter2":"DA Miller","runs":8,"balls":5},{"matchId":"980941","innings":2,"wicket":7,"batter1":"MG Johnson","batter2":"DA Miller","runs":2,"balls":3},{"matchId":"980941","innings":2,"wicket":8,"batter1":"DA Miller","batter2":"DA Miller","runs":13,"balls":6},{"matchId":"980943","innings":1,"wicket":1,"batter1":"DA Warner","batter2":"S Dhawan","runs":0,"balls":4},{"matchId":"980943","innings":1,"wicket":2,"batter1":"AP Tare","batter2":"S Dhawan","runs":26,"balls":26},{"matchId":"980943","innings":1,"wicket":3,"batter1":"S Dhawan","batter2":"S Dhawan","runs":1,"balls":3},{"matchId":"980943","innings":1,"wicket":4,"batter1":"S Dhawan","batter2":"DJ Hooda","runs":2,"balls":10},{"matchId":"980943","innings":1,"wicket":5,"batter1":"S Dhawan","batter2":"MC Henriques","runs":3,"balls":6},{"matchId":"980943","innings":1,"wicket":6,"batter1":"S Dhawan","batter2":"NV Ojha","runs":47,"balls":51},{"matchId":"980943","innings":1,"wicket":7,"batter1":"S Dhawan","batter2":"Bipul Sharma","runs":13,"balls":9},{"matchId":"980943","innings":1,"wicket":8,"batter1":"S Dhawan","batter2":"B Kumar","runs":23,"balls":9},{"matchId":"980943","innings":1,"wicket":9,"batter1":"S Dhawan","batter2":"A Nehra","runs":3,"balls":2},{"matchId":"980943","innings":2,"wicket":1,"batter1":"AM Rahane","batter2":"F du Plessis","runs":0,"balls":5},{"matchId":"980943","innings":2,"wicket":2,"batter1":"SPD Smith","batter2":"F du Plessis","runs":80,"balls":50},{"matchId":"980943","innings":2,"wicket":3,"batter1":"SPD Smith","batter2":"MS Dhoni","runs":14,"balls":11},{"matchId":"980945","innings":1,"wicket":1,"batter1":"DR Smith","batter2":"BB McCullum","runs":112,"balls":64},{"matchId":"980945","innings":1,"wicket":2,"batter1":"SK Raina","batter2":"BB McCullum","runs":4,"balls":4},{"matchId":"980945","innings":1,"wicket":3,"batter1":"SK Raina","batter2":"KD Karthik","runs":1,"balls":4},{"matchId":"980945","innings":1,"wicket":4,"batter1":"KD Karthik","batter2":"KD Karthik","runs":13,"balls":15},{"matchId":"980945","innings":1,"wicket":5,"batter1":"KD Karthik","batter2":"Ishan Kishan","runs":12,"balls":13},{"matchId":"980945","innings":1,"wicket":6,"batter1":"KD Karthik","batter2":"DJ Bravo","runs":0,"balls":1},{"matchId":"980945","innings":1,"wicket":7,"batter1":"JP Faulkner","batter2":"DJ Bravo","runs":30,"balls":19},{"matchId":"980945","innings":2,"wicket":1,"batter1":"Q de Kock","batter2":"SV Samson","runs":2,"balls":9},{"matchId":"980945","innings":2,"wicket":2,"batter1":"Q de Kock","batter2":"KK Nair","runs":10,"balls":13},{"matchId":"980945","innings":2,"wicket":3,"batter1":"KK Nair","batter2":"KK Nair","runs":4,"balls":2},{"matchId":"980945","innings":2,"wicket":4,"batter1":"JP Duminy","batter2":"KK Nair","runs":41,"balls":40},{"matchId":"980945","innings":2,"wicket":5,"batter1":"JP Duminy","batter2":"CH Morris","runs":87,"balls":39},{"matchId":"980945","innings":2,"wicket":6,"batter1":"CH Morris","batter2":"CH Morris","runs":27,"balls":17},{"matchId":"980947","innings":1,"wicket":1,"batter1":"RV Uthappa","batter2":"G Gambhir","runs":69,"balls":46},{"matchId":"980947","innings":1,"wicket":2,"batter1":"G Gambhir","batter2":"G Gambhir","runs":8,"balls":7},{"matchId":"980947","innings":1,"wicket":3,"batter1":"G Gambhir","batter2":"SA Yadav","runs":44,"balls":30},{"matchId":"980947","innings":1,"wicket":4,"batter1":"AD Russell","batter2":"SA Yadav","runs":9,"balls":12},{"matchId":"980947","innings":1,"wicket":5,"batter1":"AD Russell","batter2":"CA Lynn","runs":15,"balls":9},{"matchId":"980947","innings":1,"wicket":6,"batter1":"YK Pathan","batter2":"CA Lynn","runs":29,"balls":16},{"matchId":"980947","innings":2,"wicket":1,"batter1":"RG Sharma","batter2":"PA Patel","runs":8,"balls":7},{"matchId":"980947","innings":2,"wicket":2,"batter1":"RG Sharma","batter2":"AT Rayudu","runs":59,"balls":34},{"matchId":"980947","innings":2,"wicket":3,"batter1":"RG Sharma","batter2":"KH Pandya","runs":11,"balls":13},{"matchId":"980947","innings":2,"wicket":4,"batter1":"RG Sharma","batter2":"JC Buttler","runs":28,"balls":24},{"matchId":"980947","innings":2,"wicket":5,"batter1":"RG Sharma","batter2":"KA Pollard","runs":72,"balls":30},{"matchId":"980949","innings":1,"wicket":1,"batter1":"AM Rahane","batter2":"SS Tiwary","runs":13,"balls":15},{"matchId":"980949","innings":1,"wicket":2,"batter1":"AM Rahane","batter2":"SPD Smith","runs":111,"balls":68},{"matchId":"980949","innings":1,"wicket":3,"batter1":"SPD Smith","batter2":"SPD Smith","runs":64,"balls":35},{"matchId":"980949","innings":1,"wicket":4,"batter1":"NLTC Perera","batter2":"SPD Smith","runs":7,"balls":3},{"matchId":"980949","innings":2,"wicket":1,"batter1":"DR Smith","batter2":"BB McCullum","runs":93,"balls":49},{"matchId":"980949","innings":2,"wicket":2,"batter1":"DR Smith","batter2":"SK Raina","runs":22,"balls":16},{"matchId":"980949","innings":2,"wicket":3,"batter1":"KD Karthik","batter2":"SK Raina","runs":51,"balls":33},{"matchId":"980949","innings":2,"wicket":4,"batter1":"SK Raina","batter2":"SK Raina","runs":14,"balls":12},{"matchId":"980949","innings":2,"wicket":5,"batter1":"SK Raina","batter2":"RA Jadeja","runs":0,"balls":1},{"matchId":"980949","innings":2,"wicket":6,"batter1":"SK Raina","batter2":"JP Faulkner","runs":13,"balls":6},{"matchId":"980949","innings":2,"wicket":7,"batter1":"Ishan Kishan","batter2":"JP Faulkner","runs":0,"balls":1},{"matchId":"980949","innings":2,"wicket":8,"batter1":"JP Faulkner","batter2":"JP Faulkner","runs":3,"balls":2},{"matchId":"980951","innings":1,"wicket":1,"batter1":"Q de Kock","batter2":"SS Iyer","runs":1,"balls":3},{"matchId":"980951","innings":1,"wicket":2,"batter1":"Q de Kock","batter2":"SV Samson","runs":1,"balls":2},{"matchId":"980951","innings":1,"wicket":3,"batter1":"KK Nair","batter2":"SV Samson","runs":30,"balls":25},{"matchId":"980951","innings":1,"wicket":4,"batter1":"KK Nair","batter2":"SW Billings","runs":105,"balls":69},{"matchId":"980951","innings":1,"wicket":5,"batter1":"CH Morris","batter2":"SW Billings","runs":0,"balls":2},{"matchId":"980951","innings":1,"wicket":6,"batter1":"CR Brathwaite","batter2":"SW Billings","runs":37,"balls":12},{"matchId":"980951","innings":1,"wicket":7,"batter1":"CR Brathwaite","batter2":"RR Pant","runs":8,"balls":4},{"matchId":"980951","innings":1,"wicket":8,"batter1":"Mohammed Shami","batter2":"RR Pant","runs":4,"balls":4},{"matchId":"980951","innings":2,"wicket":1,"batter1":"RV Uthappa","batter2":"G Gambhir","runs":21,"balls":18},{"matchId":"980951","innings":2,"wicket":2,"batter1":"RV Uthappa","batter2":"PP Chawla","runs":12,"balls":10},{"matchId":"980951","innings":2,"wicket":3,"batter1":"RV Uthappa","batter2":"YK Pathan","runs":25,"balls":19},{"matchId":"980951","innings":2,"wicket":4,"batter1":"RV Uthappa","batter2":"SA Yadav","runs":36,"balls":23},{"matchId":"980951","innings":2,"wicket":5,"batter1":"RV Uthappa","batter2":"R Sathish","runs":13,"balls":13},{"matchId":"980951","innings":2,"wicket":6,"batter1":"RV Uthappa","batter2":"AD Russell","runs":44,"balls":21},{"matchId":"980951","innings":2,"wicket":7,"batter1":"RV Uthappa","batter2":"JO Holder","runs":1,"balls":2},{"matchId":"980951","innings":2,"wicket":8,"batter1":"RV Uthappa","batter2":"UT Yadav","runs":1,"balls":2},{"matchId":"980951","innings":2,"wicket":9,"batter1":"SP Narine","batter2":"UT Yadav","runs":6,"balls":4},{"matchId":"980951","innings":2,"wicket":10,"batter1":"UT Yadav","batter2":"UT Yadav","runs":0,"balls":1},{"matchId":"980953","innings":1,"wicket":1,"batter1":"DA Warner","batter2":"S Dhawan","runs":28,"balls":22},{"matchId":"980953","innings":1,"wicket":2,"batter1":"DA Warner","batter2":"KS Williamson","runs":124,"balls":74},{"matchId":"980953","innings":1,"wicket":3,"batter1":"MC Henriques","batter2":"KS Williamson","runs":8,"balls":6},{"matchId":"980953","innings":1,"wicket":4,"batter1":"MC Henriques","batter2":"NV Ojha","runs":1,"balls":3},{"matchId":"980953","innings":1,"wicket":5,"batter1":"MC Henriques","batter2":"DJ Hooda","runs":29,"balls":11},{"matchId":"980953","innings":1,"wicket":6,"batter1":"MC Henriques","batter2":"A Ashish Reddy","runs":4,"balls":5},{"matchId":"980953","innings":2,"wicket":1,"batter1":"V Kohli","batter2":"KL Rahul","runs":42,"balls":32},{"matchId":"980953","innings":2,"wicket":2,"batter1":"AB de Villiers","batter2":"KL Rahul","runs":41,"balls":28},{"matchId":"980953","innings":2,"wicket":3,"batter1":"AB de Villiers","batter2":"SR Watson","runs":7,"balls":8},{"matchId":"980953","innings":2,"wicket":4,"batter1":"AB de Villiers","batter2":"Sachin Baby","runs":39,"balls":20},{"matchId":"980953","innings":2,"wicket":5,"batter1":"Sachin Baby","batter2":"Sachin Baby","runs":23,"balls":15},{"matchId":"980953","innings":2,"wicket":6,"batter1":"KM Jadhav","batter2":"Sachin Baby","runs":27,"balls":17},{"matchId":"980955","innings":1,"wicket":1,"batter1":"M Vijay","batter2":"MP Stoinis","runs":65,"balls":40},{"matchId":"980955","innings":1,"wicket":2,"batter1":"M Vijay","batter2":"SE Marsh","runs":5,"balls":7},{"matchId":"980955","innings":1,"wicket":3,"batter1":"M Vijay","batter2":"GJ Maxwell","runs":0,"balls":1},{"matchId":"980955","innings":1,"wicket":4,"batter1":"M Vijay","batter2":"Gurkeerat Singh","runs":3,"balls":5},{"matchId":"980955","innings":1,"wicket":5,"batter1":"M Vijay","batter2":"DA Miller","runs":27,"balls":26},{"matchId":"980955","innings":1,"wicket":6,"batter1":"WP Saha","batter2":"DA Miller","runs":39,"balls":25},{"matchId":"980955","innings":1,"wicket":7,"batter1":"WP Saha","batter2":"AR Patel","runs":6,"balls":6},{"matchId":"980955","innings":1,"wicket":8,"batter1":"WP Saha","batter2":"MM Sharma","runs":6,"balls":3},{"matchId":"980955","innings":1,"wicket":9,"batter1":"KC Cariappa","batter2":"MM Sharma","runs":2,"balls":4},{"matchId":"980955","innings":1,"wicket":10,"batter1":"KC Cariappa","batter2":"Sandeep Sharma","runs":1,"balls":2},{"matchId":"980955","innings":2,"wicket":1,"batter1":"DR Smith","batter2":"BB McCullum","runs":13,"balls":10},{"matchId":"980955","innings":2,"wicket":2,"batter1":"DR Smith","batter2":"SK Raina","runs":21,"balls":20},{"matchId":"980955","innings":2,"wicket":3,"batter1":"DR Smith","batter2":"KD Karthik","runs":4,"balls":9},{"matchId":"980955","innings":2,"wicket":4,"batter1":"RA Jadeja","batter2":"KD Karthik","runs":1,"balls":2},{"matchId":"980955","innings":2,"wicket":5,"batter1":"RA Jadeja","batter2":"DJ Bravo","runs":0,"balls":1},{"matchId":"980955","innings":2,"wicket":6,"batter1":"RA Jadeja","batter2":"Ishan Kishan","runs":18,"balls":19},{"matchId":"980955","innings":2,"wicket":7,"batter1":"JP Faulkner","batter2":"Ishan Kishan","runs":29,"balls":28},{"matchId":"980955","innings":2,"wicket":8,"batter1":"JP Faulkner","batter2":"P Kumar","runs":39,"balls":25},{"matchId":"980955","innings":2,"wicket":9,"batter1":"JP Faulkner","batter2":"DS Kulkarni","runs":0,"balls":2},{"matchId":"980955","innings":2,"wicket":10,"batter1":"DS Kulkarni","batter2":"DS Kulkarni","runs":6,"balls":4},{"matchId":"980957","innings":1,"wicket":1,"batter1":"AM Rahane","batter2":"SS Tiwary","runs":8,"balls":11},{"matchId":"980957","innings":1,"wicket":2,"batter1":"SS Tiwary","batter2":"SS Tiwary","runs":84,"balls":45},{"matchId":"980957","innings":1,"wicket":3,"batter1":"SS Tiwary","batter2":"PSP Handscomb","runs":13,"balls":17},{"matchId":"980957","innings":1,"wicket":4,"batter1":"SS Tiwary","batter2":"MS Dhoni","runs":33,"balls":32},{"matchId":"980957","innings":1,"wicket":5,"batter1":"MS Dhoni","batter2":"MS Dhoni","runs":11,"balls":11},{"matchId":"980957","innings":1,"wicket":6,"batter1":"NLTC Perera","batter2":"MS Dhoni","runs":10,"balls":4},{"matchId":"980957","innings":2,"wicket":1,"batter1":"RG Sharma","batter2":"PA Patel","runs":39,"balls":24},{"matchId":"980957","innings":2,"wicket":2,"batter1":"RG Sharma","batter2":"AT Rayudu","runs":52,"balls":46},{"matchId":"980957","innings":2,"wicket":3,"batter1":"RG Sharma","batter2":"JC Buttler","runs":70,"balls":41},{"matchId":"980959","innings":1,"wicket":1,"batter1":"KL Rahul","batter2":"CH Gayle","runs":8,"balls":9},{"matchId":"980959","innings":1,"wicket":2,"batter1":"KL Rahul","batter2":"V Kohli","runs":84,"balls":58},{"matchId":"980959","innings":1,"wicket":3,"batter1":"V Kohli","batter2":"V Kohli","runs":17,"balls":15},{"matchId":"980959","innings":1,"wicket":4,"batter1":"V Kohli","batter2":"SR Watson","runs":20,"balls":18},{"matchId":"980959","innings":1,"wicket":5,"batter1":"SR Watson","batter2":"SR Watson","runs":38,"balls":16},{"matchId":"980959","innings":1,"wicket":6,"batter1":"SR Watson","batter2":"STR Binny","runs":17,"balls":5},{"matchId":"980959","innings":1,"wicket":7,"batter1":"SR Watson","batter2":"VR Aaron","runs":1,"balls":1},{"matchId":"980959","innings":2,"wicket":1,"batter1":"RV Uthappa","batter2":"G Gambhir","runs":6,"balls":6},{"matchId":"980959","innings":2,"wicket":2,"batter1":"G Gambhir","batter2":"G Gambhir","runs":28,"balls":22},{"matchId":"980959","innings":2,"wicket":3,"batter1":"G Gambhir","batter2":"MK Pandey","runs":32,"balls":26},{"matchId":"980959","innings":2,"wicket":4,"batter1":"MK Pandey","batter2":"MK Pandey","runs":3,"balls":7},{"matchId":"980959","innings":2,"wicket":5,"batter1":"YK Pathan","batter2":"MK Pandey","runs":96,"balls":44},{"matchId":"980959","innings":2,"wicket":6,"batter1":"YK Pathan","batter2":"SA Yadav","runs":24,"balls":10},{"matchId":"980961","innings":1,"wicket":1,"batter1":"DR Smith","batter2":"BB McCullum","runs":17,"balls":17},{"matchId":"980961","innings":1,"wicket":2,"batter1":"DR Smith","batter2":"AJ Finch","runs":0,"balls":2},{"matchId":"980961","innings":1,"wicket":3,"batter1":"AJ Finch","batter2":"AJ Finch","runs":7,"balls":5},{"matchId":"980961","innings":1,"wicket":4,"batter1":"SK Raina","batter2":"AJ Finch","runs":51,"balls":42},{"matchId":"980961","innings":1,"wicket":5,"batter1":"KD Karthik","batter2":"AJ Finch","runs":52,"balls":39},{"matchId":"980961","innings":1,"wicket":6,"batter1":"JP Faulkner","batter2":"AJ Finch","runs":11,"balls":9},{"matchId":"980961","innings":1,"wicket":7,"batter1":"RA Jadeja","batter2":"AJ Finch","runs":11,"balls":6},{"matchId":"980961","innings":2,"wicket":1,"batter1":"Q de Kock","batter2":"RR Pant","runs":115,"balls":81},{"matchId":"980961","innings":2,"wicket":2,"batter1":"Q de Kock","batter2":"SV Samson","runs":6,"balls":8},{"matchId":"980961","innings":2,"wicket":3,"batter1":"JP Duminy","batter2":"SV Samson","runs":29,"balls":16},{"matchId":"980963","innings":1,"wicket":1,"batter1":"RV Uthappa","batter2":"G Gambhir","runs":101,"balls":81},{"matchId":"980963","innings":1,"wicket":2,"batter1":"RV Uthappa","batter2":"YK Pathan","runs":36,"balls":20},{"matchId":"980963","innings":1,"wicket":3,"batter1":"YK Pathan","batter2":"YK Pathan","runs":27,"balls":19},{"matchId":"980963","innings":2,"wicket":1,"batter1":"M Vijay","batter2":"MP Stoinis","runs":1,"balls":4},{"matchId":"980963","innings":2,"wicket":2,"batter1":"M Vijay","batter2":"M Vohra","runs":12,"balls":14},{"matchId":"980963","innings":2,"wicket":3,"batter1":"M Vijay","batter2":"WP Saha","runs":0,"balls":1},{"matchId":"980963","innings":2,"wicket":4,"batter1":"GJ Maxwell","batter2":"WP Saha","runs":40,"balls":35},{"matchId":"980963","innings":2,"wicket":5,"batter1":"GJ Maxwell","batter2":"DA Miller","runs":67,"balls":40},{"matchId":"980963","innings":2,"wicket":6,"batter1":"Gurkeerat Singh","batter2":"DA Miller","runs":10,"balls":11},{"matchId":"980963","innings":2,"wicket":7,"batter1":"Gurkeerat Singh","batter2":"AR Patel","runs":24,"balls":11},{"matchId":"980963","innings":2,"wicket":8,"batter1":"Gurkeerat Singh","batter2":"Swapnil Singh","runs":1,"balls":1},{"matchId":"980963","innings":2,"wicket":9,"batter1":"MM Sharma","batter2":"Swapnil Singh","runs":1,"balls":2},{"matchId":"980963","innings":2,"wicket":10,"batter1":"MM Sharma","batter2":"Sandeep Sharma","runs":1,"balls":1},{"matchId":"980965","innings":1,"wicket":1,"batter1":"RR Pant","batter2":"SV Samson","runs":13,"balls":16},{"matchId":"980965","innings":1,"wicket":2,"batter1":"KK Nair","batter2":"SV Samson","runs":35,"balls":21},{"matchId":"980965","innings":1,"wicket":3,"batter1":"KK Nair","batter2":"JP Duminy","runs":17,"balls":22},{"matchId":"980965","innings":1,"wicket":4,"batter1":"JP Duminy","batter2":"JP Duminy","runs":45,"balls":30},{"matchId":"980965","innings":1,"wicket":5,"batter1":"JP Duminy","batter2":"CR Brathwaite","runs":27,"balls":13},{"matchId":"980965","innings":1,"wicket":6,"batter1":"JP Duminy","batter2":"P Negi","runs":1,"balls":1},{"matchId":"980965","innings":1,"wicket":7,"batter1":"P Negi","batter2":"P Negi","runs":5,"balls":5},{"matchId":"980965","innings":1,"wicket":8,"batter1":"P Negi","batter2":"Mohammed Shami","runs":19,"balls":13},{"matchId":"980965","innings":2,"wicket":1,"batter1":"AM Rahane","batter2":"UT Khawaja","runs":59,"balls":50},{"matchId":"980965","innings":2,"wicket":2,"batter1":"AM Rahane","batter2":"SS Tiwary","runs":45,"balls":32},{"matchId":"980965","innings":2,"wicket":3,"batter1":"AM Rahane","batter2":"MS Dhoni","runs":42,"balls":29},{"matchId":"980965","innings":2,"wicket":4,"batter1":"AM Rahane","batter2":"NLTC Perera","runs":20,"balls":7},{"matchId":"980967","innings":1,"wicket":1,"batter1":"DR Smith","batter2":"BB McCullum","runs":2,"balls":16},{"matchId":"980967","innings":1,"wicket":2,"batter1":"SK Raina","batter2":"BB McCullum","runs":22,"balls":14},{"matchId":"980967","innings":1,"wicket":3,"batter1":"BB McCullum","batter2":"BB McCullum","runs":1,"balls":4},{"matchId":"980967","innings":1,"wicket":4,"batter1":"BB McCullum","batter2":"AJ Finch","runs":9,"balls":12},{"matchId":"980967","innings":1,"wicket":5,"batter1":"AJ Finch","batter2":"AJ Finch","runs":45,"balls":39},{"matchId":"980967","innings":1,"wicket":6,"batter1":"AJ Finch","batter2":"RA Jadeja","runs":27,"balls":24},{"matchId":"980967","innings":1,"wicket":7,"batter1":"AJ Finch","batter2":"P Kumar","runs":20,"balls":11},{"matchId":"980967","innings":2,"wicket":1,"batter1":"DA Warner","batter2":"S Dhawan","runs":26,"balls":19},{"matchId":"980967","innings":2,"wicket":2,"batter1":"KS Williamson","batter2":"S Dhawan","runs":7,"balls":10},{"matchId":"980967","innings":2,"wicket":3,"batter1":"MC Henriques","batter2":"S Dhawan","runs":22,"balls":27},{"matchId":"980967","innings":2,"wicket":4,"batter1":"Yuvraj Singh","batter2":"S Dhawan","runs":26,"balls":28},{"matchId":"980967","innings":2,"wicket":5,"batter1":"DJ Hooda","batter2":"S Dhawan","runs":27,"balls":20},{"matchId":"980967","innings":2,"wicket":6,"batter1":"NV Ojha","batter2":"S Dhawan","runs":21,"balls":10},{"matchId":"980969","innings":1,"wicket":1,"batter1":"AM Rahane","batter2":"UT Khawaja","runs":26,"balls":14},{"matchId":"980969","innings":1,"wicket":2,"batter1":"AM Rahane","batter2":"SS Tiwary","runs":106,"balls":70},{"matchId":"980969","innings":1,"wicket":3,"batter1":"AM Rahane","batter2":"MS Dhoni","runs":12,"balls":10},{"matchId":"980969","innings":1,"wicket":4,"batter1":"AM Rahane","batter2":"NLTC Perera","runs":27,"balls":14},{"matchId":"980969","innings":1,"wicket":5,"batter1":"AM Rahane","batter2":"GJ Bailey","runs":0,"balls":1},{"matchId":"980969","innings":1,"wicket":6,"batter1":"R Bhatia","batter2":"GJ Bailey","runs":3,"balls":4},{"matchId":"980969","innings":1,"wicket":7,"batter1":"R Bhatia","batter2":"R Ashwin","runs":17,"balls":7},{"matchId":"980969","innings":2,"wicket":1,"batter1":"V Kohli","batter2":"KL Rahul","runs":94,"balls":67},{"matchId":"980969","innings":2,"wicket":2,"batter1":"V Kohli","batter2":"AB de Villiers","runs":3,"balls":5},{"matchId":"980969","innings":2,"wicket":3,"batter1":"V Kohli","batter2":"SR Watson","runs":46,"balls":21},{"matchId":"980969","innings":2,"wicket":4,"batter1":"V Kohli","batter2":"TM Head","runs":52,"balls":25},{"matchId":"980971","innings":1,"wicket":1,"batter1":"M Vijay","batter2":"MP Stoinis","runs":45,"balls":34},{"matchId":"980971","innings":1,"wicket":2,"batter1":"HM Amla","batter2":"MP Stoinis","runs":3,"balls":8},{"matchId":"980971","innings":1,"wicket":3,"batter1":"MP Stoinis","batter2":"MP Stoinis","runs":58,"balls":41},{"matchId":"980971","innings":1,"wicket":4,"batter1":"WP Saha","batter2":"MP Stoinis","runs":46,"balls":25},{"matchId":"980971","innings":1,"wicket":5,"batter1":"WP Saha","batter2":"DA Miller","runs":0,"balls":1},{"matchId":"980971","innings":1,"wicket":6,"batter1":"DA Miller","batter2":"DA Miller","runs":29,"balls":11},{"matchId":"980971","innings":2,"wicket":1,"batter1":"Q de Kock","batter2":"SV Samson","runs":70,"balls":47},{"matchId":"980971","innings":2,"wicket":2,"batter1":"KK Nair","batter2":"SV Samson","runs":51,"balls":35},{"matchId":"980971","innings":2,"wicket":3,"batter1":"KK Nair","batter2":"SW Billings","runs":13,"balls":11},{"matchId":"980971","innings":2,"wicket":4,"batter1":"SW Billings","batter2":"SW Billings","runs":7,"balls":8},{"matchId":"980971","innings":2,"wicket":5,"batter1":"CH Morris","batter2":"SW Billings","runs":12,"balls":6},{"matchId":"980971","innings":2,"wicket":6,"batter1":"CH Morris","batter2":"RR Pant","runs":19,"balls":13},{"matchId":"980973","innings":1,"wicket":1,"batter1":"DA Warner","batter2":"S Dhawan","runs":85,"balls":59},{"matchId":"980973","innings":1,"wicket":2,"batter1":"KS Williamson","batter2":"S Dhawan","runs":6,"balls":10},{"matchId":"980973","innings":1,"wicket":3,"batter1":"Yuvraj Singh","batter2":"S Dhawan","runs":85,"balls":49},{"matchId":"980973","innings":1,"wicket":4,"batter1":"MC Henriques","batter2":"S Dhawan","runs":1,"balls":2},{"matchId":"980973","innings":2,"wicket":1,"batter1":"RG Sharma","batter2":"PA Patel","runs":5,"balls":6},{"matchId":"980973","innings":2,"wicket":2,"batter1":"RG Sharma","batter2":"AT Rayudu","runs":0,"balls":1},{"matchId":"980973","innings":2,"wicket":3,"batter1":"KH Pandya","batter2":"AT Rayudu","runs":23,"balls":15},{"matchId":"980973","innings":2,"wicket":4,"batter1":"KH Pandya","batter2":"JC Buttler","runs":2,"balls":2},{"matchId":"980973","innings":2,"wicket":5,"batter1":"KH Pandya","batter2":"KA Pollard","runs":0,"balls":2},{"matchId":"980973","innings":2,"wicket":6,"batter1":"HH Pandya","batter2":"KA Pollard","runs":19,"balls":26},{"matchId":"980973","innings":2,"wicket":7,"batter1":"HH Pandya","batter2":"Harbhajan Singh","runs":1,"balls":3},{"matchId":"980973","innings":2,"wicket":8,"batter1":"TG Southee","batter2":"Harbhajan Singh","runs":8,"balls":12},{"matchId":"980973","innings":2,"wicket":9,"batter1":"MJ McClenaghan","batter2":"Harbhajan Singh","runs":20,"balls":17},{"matchId":"980973","innings":2,"wicket":10,"batter1":"JJ Bumrah","batter2":"Harbhajan Singh","runs":14,"balls":15},{"matchId":"980975","innings":1,"wicket":1,"batter1":"RV Uthappa","batter2":"G Gambhir","runs":15,"balls":13},{"matchId":"980975","innings":1,"wicket":2,"batter1":"RV Uthappa","batter2":"MK Pandey","runs":0,"balls":2},{"matchId":"980975","innings":1,"wicket":3,"batter1":"RV Uthappa","batter2":"SA Yadav","runs":6,"balls":6},{"matchId":"980975","innings":1,"wicket":4,"batter1":"Shakib Al Hasan","batter2":"SA Yadav","runs":3,"balls":14},{"matchId":"980975","innings":1,"wicket":5,"batter1":"Shakib Al Hasan","batter2":"YK Pathan","runs":134,"balls":85},{"matchId":"980975","innings":2,"wicket":1,"batter1":"DR Smith","batter2":"BB McCullum","runs":42,"balls":33},{"matchId":"980975","innings":2,"wicket":2,"batter1":"SK Raina","batter2":"BB McCullum","runs":25,"balls":14},{"matchId":"980975","innings":2,"wicket":3,"batter1":"SK Raina","batter2":"KD Karthik","runs":49,"balls":36},{"matchId":"980975","innings":2,"wicket":4,"batter1":"KD Karthik","batter2":"KD Karthik","runs":39,"balls":16},{"matchId":"980975","innings":2,"wicket":5,"batter1":"RA Jadeja","batter2":"KD Karthik","runs":3,"balls":7},{"matchId":"980975","innings":2,"wicket":6,"batter1":"RA Jadeja","batter2":"DJ Bravo","runs":6,"balls":2},{"matchId":"980977","innings":1,"wicket":1,"batter1":"V Kohli","batter2":"KL Rahul","runs":63,"balls":45},{"matchId":"980977","innings":1,"wicket":2,"batter1":"V Kohli","batter2":"AB de Villiers","runs":1,"balls":2},{"matchId":"980977","innings":1,"wicket":3,"batter1":"SR Watson","batter2":"AB de Villiers","runs":3,"balls":5},{"matchId":"980977","innings":1,"wicket":4,"batter1":"Sachin Baby","batter2":"AB de Villiers","runs":88,"balls":55},{"matchId":"980977","innings":1,"wicket":5,"batter1":"Sachin Baby","batter2":"TM Head","runs":19,"balls":12},{"matchId":"980977","innings":1,"wicket":6,"batter1":"Sachin Baby","batter2":"STR Binny","runs":1,"balls":1},{"matchId":"980977","innings":2,"wicket":1,"batter1":"HM Amla","batter2":"M Vijay","runs":45,"balls":33},{"matchId":"980977","innings":2,"wicket":2,"batter1":"WP Saha","batter2":"M Vijay","runs":43,"balls":32},{"matchId":"980977","innings":2,"wicket":3,"batter1":"DA Miller","batter2":"M Vijay","runs":0,"balls":1},{"matchId":"980977","innings":2,"wicket":4,"batter1":"M Vijay","batter2":"M Vijay","runs":51,"balls":36},{"matchId":"980977","innings":2,"wicket":5,"batter1":"F Behardien","batter2":"M Vijay","runs":35,"balls":18},{"matchId":"980979","innings":1,"wicket":1,"batter1":"DA Warner","batter2":"S Dhawan","runs":18,"balls":20},{"matchId":"980979","innings":1,"wicket":2,"batter1":"KS Williamson","batter2":"S Dhawan","runs":46,"balls":42},{"matchId":"980979","innings":1,"wicket":3,"batter1":"KS Williamson","batter2":"Yuvraj Singh","runs":32,"balls":30},{"matchId":"980979","innings":1,"wicket":4,"batter1":"KS Williamson","batter2":"MC Henriques","runs":18,"balls":14},{"matchId":"980979","innings":1,"wicket":5,"batter1":"MC Henriques","batter2":"MC Henriques","runs":0,"balls":1},{"matchId":"980979","innings":1,"wicket":6,"batter1":"NV Ojha","batter2":"MC Henriques","runs":21,"balls":9},{"matchId":"980979","innings":1,"wicket":7,"batter1":"NV Ojha","batter2":"B Kumar","runs":1,"balls":2},{"matchId":"980979","innings":1,"wicket":8,"batter1":"BB Sran","batter2":"B Kumar","runs":1,"balls":2},{"matchId":"980979","innings":2,"wicket":1,"batter1":"AM Rahane","batter2":"UT Khawaja","runs":0,"balls":3},{"matchId":"980979","innings":2,"wicket":2,"batter1":"GJ Bailey","batter2":"UT Khawaja","runs":19,"balls":21},{"matchId":"980979","innings":2,"wicket":3,"batter1":"GJ Bailey","batter2":"R Ashwin","runs":49,"balls":48},{"matchId":"980979","innings":2,"wicket":4,"batter1":"SS Tiwary","batter2":"R Ashwin","runs":10,"balls":8},{"matchId":"980979","innings":2,"wicket":5,"batter1":"SS Tiwary","batter2":"MS Dhoni","runs":8,"balls":10},{"matchId":"980979","innings":2,"wicket":6,"batter1":"MS Dhoni","batter2":"MS Dhoni","runs":40,"balls":27},{"matchId":"980979","innings":2,"wicket":7,"batter1":"MS Dhoni","batter2":"R Bhatia","runs":7,"balls":2},{"matchId":"980979","innings":2,"wicket":8,"batter1":"A Zampa","batter2":"R Bhatia","runs":0,"balls":1},{"matchId":"980981","innings":1,"wicket":1,"batter1":"V Kohli","batter2":"CH Gayle","runs":8,"balls":7},{"matchId":"980981","innings":1,"wicket":2,"batter1":"AB de Villiers","batter2":"CH Gayle","runs":9,"balls":15},{"matchId":"980981","innings":1,"wicket":3,"batter1":"AB de Villiers","batter2":"KL Rahul","runs":43,"balls":39},{"matchId":"980981","innings":1,"wicket":4,"batter1":"KL Rahul","batter2":"KL Rahul","runs":38,"balls":32},{"matchId":"980981","innings":1,"wicket":5,"batter1":"KL Rahul","batter2":"Sachin Baby","runs":53,"balls":27},{"matchId":"980981","innings":2,"wicket":1,"batter1":"RG Sharma","batter2":"PA Patel","runs":2,"balls":7},{"matchId":"980981","innings":2,"wicket":2,"batter1":"RG Sharma","batter2":"AT Rayudu","runs":58,"balls":51},{"matchId":"980981","innings":2,"wicket":3,"batter1":"N Rana","batter2":"AT Rayudu","runs":19,"balls":21},{"matchId":"980981","innings":2,"wicket":4,"batter1":"KA Pollard","batter2":"AT Rayudu","runs":19,"balls":13},{"matchId":"980981","innings":2,"wicket":5,"batter1":"KA Pollard","batter2":"JC Buttler","runs":55,"balls":22},{"matchId":"980983","innings":1,"wicket":1,"batter1":"DA Warner","batter2":"S Dhawan","runs":67,"balls":53},{"matchId":"980983","innings":1,"wicket":2,"batter1":"KS Williamson","batter2":"S Dhawan","runs":31,"balls":25},{"matchId":"980983","innings":1,"wicket":3,"batter1":"KS Williamson","batter2":"Yuvraj Singh","runs":15,"balls":12},{"matchId":"980983","innings":1,"wicket":4,"batter1":"KS Williamson","batter2":"MC Henriques","runs":1,"balls":2},{"matchId":"980983","innings":1,"wicket":5,"batter1":"KS Williamson","batter2":"DJ Hooda","runs":21,"balls":16},{"matchId":"980983","innings":1,"wicket":6,"batter1":"KS Williamson","batter2":"NV Ojha","runs":2,"balls":4},{"matchId":"980983","innings":1,"wicket":7,"batter1":"B Kumar","batter2":"NV Ojha","runs":1,"balls":3},{"matchId":"980983","innings":1,"wicket":8,"batter1":"NV Ojha","batter2":"NV Ojha","runs":5,"balls":5},{"matchId":"980983","innings":1,"wicket":9,"batter1":"BB Sran","batter2":"NV Ojha","runs":3,"balls":2},{"matchId":"980983","innings":2,"wicket":1,"batter1":"Q de Kock","batter2":"MA Agarwal","runs":20,"balls":19},{"matchId":"980983","innings":2,"wicket":2,"batter1":"Q de Kock","batter2":"KK Nair","runs":55,"balls":37},{"matchId":"980983","innings":2,"wicket":3,"batter1":"Q de Kock","batter2":"SV Samson","runs":3,"balls":3},{"matchId":"980983","innings":2,"wicket":4,"batter1":"RR Pant","batter2":"SV Samson","runs":72,"balls":50},{"matchId":"980985","innings":1,"wicket":1,"batter1":"RG Sharma","batter2":"UBT Chand","runs":7,"balls":12},{"matchId":"980985","innings":1,"wicket":2,"batter1":"RG Sharma","batter2":"AT Rayudu","runs":1,"balls":5},{"matchId":"980985","innings":1,"wicket":3,"batter1":"RG Sharma","batter2":"N Rana","runs":28,"balls":36},{"matchId":"980985","innings":1,"wicket":4,"batter1":"JC Buttler","batter2":"N Rana","runs":11,"balls":11},{"matchId":"980985","innings":1,"wicket":5,"batter1":"JC Buttler","batter2":"KA Pollard","runs":14,"balls":17},{"matchId":"980985","innings":1,"wicket":6,"batter1":"KA Pollard","batter2":"KA Pollard","runs":42,"balls":19},{"matchId":"980985","innings":1,"wicket":7,"batter1":"KA Pollard","batter2":"Harbhajan Singh","runs":0,"balls":1},{"matchId":"980985","innings":1,"wicket":8,"batter1":"TG Southee","batter2":"Harbhajan Singh","runs":1,"balls":3},{"matchId":"980985","innings":1,"wicket":9,"batter1":"Harbhajan Singh","batter2":"Harbhajan Singh","runs":10,"balls":7},{"matchId":"980985","innings":1,"wicket":10,"batter1":"Harbhajan Singh","batter2":"JJ Bumrah","runs":10,"balls":9},{"matchId":"980985","innings":2,"wicket":1,"batter1":"M Vijay","batter2":"HM Amla","runs":1,"balls":6},{"matchId":"980985","innings":2,"wicket":2,"batter1":"M Vijay","batter2":"WP Saha","runs":116,"balls":88},{"matchId":"980985","innings":2,"wicket":3,"batter1":"M Vijay","batter2":"GJ Maxwell","runs":1,"balls":1},{"matchId":"980985","innings":2,"wicket":4,"batter1":"M Vijay","batter2":"Gurkeerat Singh","runs":9,"balls":7},{"matchId":"980987","innings":1,"wicket":1,"batter1":"CH Gayle","batter2":"V Kohli","runs":19,"balls":23},{"matchId":"980987","innings":1,"wicket":2,"batter1":"AB de Villiers","batter2":"V Kohli","runs":229,"balls":97},{"matchId":"980987","innings":1,"wicket":3,"batter1":"AB de Villiers","batter2":"SR Watson","runs":0,"balls":1},{"matchId":"980987","innings":2,"wicket":1,"batter1":"DR Smith","batter2":"BB McCullum","runs":9,"balls":11},{"matchId":"980987","innings":2,"wicket":2,"batter1":"RA Jadeja","batter2":"BB McCullum","runs":28,"balls":19},{"matchId":"980987","innings":2,"wicket":3,"batter1":"RA Jadeja","batter2":"KD Karthik","runs":7,"balls":11},{"matchId":"980987","innings":2,"wicket":4,"batter1":"RA Jadeja","batter2":"AJ Finch","runs":0,"balls":1},{"matchId":"980987","innings":2,"wicket":5,"batter1":"AJ Finch","batter2":"AJ Finch","runs":3,"balls":5},{"matchId":"980987","innings":2,"wicket":6,"batter1":"AJ Finch","batter2":"AD Nath","runs":21,"balls":21},{"matchId":"980987","innings":2,"wicket":7,"batter1":"AJ Finch","batter2":"P Kumar","runs":1,"balls":5},{"matchId":"980987","innings":2,"wicket":8,"batter1":"AJ Finch","batter2":"DS Kulkarni","runs":5,"balls":4},{"matchId":"980987","innings":2,"wicket":9,"batter1":"AJ Finch","batter2":"PV Tambe","runs":30,"balls":37},{"matchId":"980987","innings":2,"wicket":10,"batter1":"S Kaushik","batter2":"PV Tambe","runs":0,"balls":1},{"matchId":"980989","innings":1,"wicket":1,"batter1":"AM Rahane","batter2":"UT Khawaja","runs":19,"balls":17},{"matchId":"980989","innings":1,"wicket":2,"batter1":"GJ Bailey","batter2":"UT Khawaja","runs":7,"balls":11},{"matchId":"980989","innings":1,"wicket":3,"batter1":"GJ Bailey","batter2":"SS Tiwary","runs":41,"balls":31},{"matchId":"980989","innings":1,"wicket":4,"batter1":"GJ Bailey","batter2":"IK Pathan","runs":7,"balls":5},{"matchId":"980989","innings":1,"wicket":5,"batter1":"MS Dhoni","batter2":"IK Pathan","runs":13,"balls":20},{"matchId":"980989","innings":1,"wicket":6,"batter1":"MS Dhoni","batter2":"NLTC Perera","runs":15,"balls":15},{"matchId":"980989","innings":1,"wicket":7,"batter1":"MS Dhoni","batter2":"R Ashwin","runs":1,"balls":8},{"matchId":"980989","innings":2,"wicket":1,"batter1":"RV Uthappa","batter2":"G Gambhir","runs":5,"balls":1},{"matchId":"980989","innings":2,"wicket":2,"batter1":"MK Pandey","batter2":"G Gambhir","runs":3,"balls":2},{"matchId":"980989","innings":2,"wicket":3,"batter1":"MK Pandey","batter2":"YK Pathan","runs":58,"balls":27},{"matchId":"980991","innings":1,"wicket":1,"batter1":"HM Amla","batter2":"M Vijay","runs":33,"balls":26},{"matchId":"980991","innings":1,"wicket":2,"batter1":"HM Amla","batter2":"WP Saha","runs":54,"balls":41},{"matchId":"980991","innings":1,"wicket":3,"batter1":"HM Amla","batter2":"Gurkeerat Singh","runs":65,"balls":37},{"matchId":"980991","innings":1,"wicket":4,"batter1":"HM Amla","batter2":"DA Miller","runs":21,"balls":14},{"matchId":"980991","innings":1,"wicket":5,"batter1":"DA Miller","batter2":"DA Miller","runs":6,"balls":2},{"matchId":"980991","innings":2,"wicket":1,"batter1":"DA Warner","batter2":"S Dhawan","runs":68,"balls":49},{"matchId":"980991","innings":2,"wicket":2,"batter1":"DA Warner","batter2":"DJ Hooda","runs":29,"balls":26},{"matchId":"980991","innings":2,"wicket":3,"batter1":"Yuvraj Singh","batter2":"DJ Hooda","runs":42,"balls":23},{"matchId":"980991","innings":2,"wicket":4,"batter1":"Yuvraj Singh","batter2":"BCJ Cutting","runs":41,"balls":22},{"matchId":"980993","innings":1,"wicket":1,"batter1":"RG Sharma","batter2":"MJ Guptill","runs":46,"balls":39},{"matchId":"980993","innings":1,"wicket":2,"batter1":"KH Pandya","batter2":"MJ Guptill","runs":98,"balls":50},{"matchId":"980993","innings":1,"wicket":3,"batter1":"KH Pandya","batter2":"KA Pollard","runs":29,"balls":15},{"matchId":"980993","innings":1,"wicket":4,"batter1":"JC Buttler","batter2":"KA Pollard","runs":1,"balls":3},{"matchId":"980993","innings":1,"wicket":5,"batter1":"JC Buttler","batter2":"AT Rayudu","runs":32,"balls":13},{"matchId":"980993","innings":2,"wicket":1,"batter1":"MA Agarwal","batter2":"Q de Kock","runs":11,"balls":9},{"matchId":"980993","innings":2,"wicket":2,"batter1":"KK Nair","batter2":"Q de Kock","runs":35,"balls":19},{"matchId":"980993","innings":2,"wicket":3,"batter1":"SV Samson","batter2":"Q de Kock","runs":14,"balls":19},{"matchId":"980993","innings":2,"wicket":4,"batter1":"Q de Kock","batter2":"Q de Kock","runs":11,"balls":9},{"matchId":"980993","innings":2,"wicket":5,"batter1":"JP Duminy","batter2":"Q de Kock","runs":25,"balls":21},{"matchId":"980993","innings":2,"wicket":6,"batter1":"RR Pant","batter2":"Q de Kock","runs":0,"balls":1},{"matchId":"980993","innings":2,"wicket":7,"batter1":"CH Morris","batter2":"Q de Kock","runs":13,"balls":15},{"matchId":"980993","innings":2,"wicket":8,"batter1":"CH Morris","batter2":"S Nadeem","runs":9,"balls":7},{"matchId":"980993","innings":2,"wicket":9,"batter1":"Imran Tahir","batter2":"S Nadeem","runs":5,"balls":8},{"matchId":"980993","innings":2,"wicket":10,"batter1":"Z Khan","batter2":"S Nadeem","runs":3,"balls":7},{"matchId":"980995","innings":1,"wicket":1,"batter1":"RV Uthappa","batter2":"G Gambhir","runs":14,"balls":14},{"matchId":"980995","innings":1,"wicket":2,"batter1":"MK Pandey","batter2":"G Gambhir","runs":76,"balls":49},{"matchId":"980995","innings":1,"wicket":3,"batter1":"MK Pandey","batter2":"YK Pathan","runs":23,"balls":19},{"matchId":"980995","innings":1,"wicket":4,"batter1":"YK Pathan","batter2":"YK Pathan","runs":5,"balls":3},{"matchId":"980995","innings":1,"wicket":5,"batter1":"SA Yadav","batter2":"YK Pathan","runs":7,"balls":7},{"matchId":"980995","innings":1,"wicket":6,"batter1":"AD Russell","batter2":"YK Pathan","runs":58,"balls":28},{"matchId":"980995","innings":2,"wicket":1,"batter1":"CH Gayle","batter2":"V Kohli","runs":71,"balls":45},{"matchId":"980995","innings":2,"wicket":2,"batter1":"AB de Villiers","batter2":"V Kohli","runs":115,"balls":68},{"matchId":"980997","innings":1,"wicket":1,"batter1":"Q de Kock","batter2":"SS Iyer","runs":4,"balls":13},{"matchId":"980997","innings":1,"wicket":2,"batter1":"KK Nair","batter2":"SS Iyer","runs":21,"balls":16},{"matchId":"980997","innings":1,"wicket":3,"batter1":"KK Nair","batter2":"SV Samson","runs":24,"balls":31},{"matchId":"980997","innings":1,"wicket":4,"batter1":"KK Nair","batter2":"RR Pant","runs":13,"balls":18},{"matchId":"980997","innings":1,"wicket":5,"batter1":"KK Nair","batter2":"JP Duminy","runs":8,"balls":9},{"matchId":"980997","innings":1,"wicket":6,"batter1":"CH Morris","batter2":"JP Duminy","runs":23,"balls":23},{"matchId":"980997","innings":1,"wicket":7,"batter1":"CH Morris","batter2":"NM Coulter-Nile","runs":28,"balls":10},{"matchId":"980997","innings":2,"wicket":1,"batter1":"AM Rahane","batter2":"UT Khawaja","runs":31,"balls":22},{"matchId":"980997","innings":2,"wicket":2,"batter1":"AM Rahane","batter2":"GJ Bailey","runs":45,"balls":45},{"matchId":"980999","innings":1,"wicket":1,"batter1":"CH Gayle","batter2":"V Kohli","runs":147,"balls":67},{"matchId":"980999","innings":1,"wicket":2,"batter1":"V Kohli","batter2":"V Kohli","runs":7,"balls":4},{"matchId":"980999","innings":1,"wicket":3,"batter1":"V Kohli","batter2":"KL Rahul","runs":45,"balls":15},{"matchId":"980999","innings":1,"wicket":4,"batter1":"KL Rahul","batter2":"KL Rahul","runs":12,"balls":6},{"matchId":"980999","innings":2,"wicket":1,"batter1":"M Vijay","batter2":"HM Amla","runs":17,"balls":10},{"matchId":"980999","innings":2,"wicket":2,"batter1":"WP Saha","batter2":"HM Amla","runs":26,"balls":12},{"matchId":"980999","innings":2,"wicket":3,"batter1":"DA Miller","batter2":"HM Amla","runs":10,"balls":6},{"matchId":"980999","innings":2,"wicket":4,"batter1":"DA Miller","batter2":"Gurkeerat Singh","runs":1,"balls":3},{"matchId":"980999","innings":2,"wicket":5,"batter1":"AR Patel","batter2":"Gurkeerat Singh","runs":23,"balls":14},{"matchId":"980999","innings":2,"wicket":6,"batter1":"Gurkeerat Singh","batter2":"Gurkeerat Singh","runs":2,"balls":5},{"matchId":"980999","innings":2,"wicket":7,"batter1":"Gurkeerat Singh","batter2":"KJ Abbott","runs":1,"balls":3},{"matchId":"980999","innings":2,"wicket":8,"batter1":"Gurkeerat Singh","batter2":"MM Sharma","runs":16,"balls":12},{"matchId":"980999","innings":2,"wicket":9,"batter1":"KC Cariappa","batter2":"MM Sharma","runs":9,"balls":9},{"matchId":"980999","innings":2,"wicket":10,"batter1":"KC Cariappa","batter2":"Sandeep Sharma","runs":15,"balls":10},{"matchId":"981001","innings":1,"wicket":1,"batter1":"RV Uthappa","batter2":"G Gambhir","runs":23,"balls":19},{"matchId":"981001","innings":1,"wicket":2,"batter1":"RV Uthappa","batter2":"MK Pandey","runs":11,"balls":7},{"matchId":"981001","innings":1,"wicket":3,"batter1":"RV Uthappa","batter2":"PP Chawla","runs":10,"balls":12},{"matchId":"981001","innings":1,"wicket":4,"batter1":"YK Pathan","batter2":"PP Chawla","runs":11,"balls":18},{"matchId":"981001","innings":1,"wicket":5,"batter1":"YK Pathan","batter2":"Shakib Al Hasan","runs":6,"balls":13},{"matchId":"981001","innings":1,"wicket":6,"batter1":"YK Pathan","batter2":"SA Yadav","runs":41,"balls":32},{"matchId":"981001","innings":1,"wicket":7,"batter1":"YK Pathan","batter2":"JO Holder","runs":18,"balls":9},{"matchId":"981001","innings":1,"wicket":8,"batter1":"SP Narine","batter2":"JO Holder","runs":2,"balls":7},{"matchId":"981001","innings":1,"wicket":9,"batter1":"SP Narine","batter2":"M Morkel","runs":2,"balls":3},{"matchId":"981001","innings":2,"wicket":1,"batter1":"DR Smith","batter2":"BB McCullum","runs":0,"balls":1},{"matchId":"981001","innings":2,"wicket":2,"batter1":"SK Raina","batter2":"BB McCullum","runs":18,"balls":7},{"matchId":"981001","innings":2,"wicket":3,"batter1":"SK Raina","batter2":"KD Karthik","runs":20,"balls":15},{"matchId":"981001","innings":2,"wicket":4,"batter1":"SK Raina","batter2":"AJ Finch","runs":59,"balls":36},{"matchId":"981001","innings":2,"wicket":5,"batter1":"SK Raina","batter2":"RA Jadeja","runs":28,"balls":22},{"matchId":"981003","innings":1,"wicket":1,"batter1":"DA Warner","batter2":"S Dhawan","runs":46,"balls":36},{"matchId":"981003","innings":1,"wicket":2,"batter1":"DA Warner","batter2":"DJ Hooda","runs":2,"balls":4},{"matchId":"981003","innings":1,"wicket":3,"batter1":"DA Warner","batter2":"Yuvraj Singh","runs":18,"balls":17},{"matchId":"981003","innings":1,"wicket":4,"batter1":"DA Warner","batter2":"MC Henriques","runs":39,"balls":24},{"matchId":"981003","innings":1,"wicket":5,"batter1":"DA Warner","batter2":"EJG Morgan","runs":12,"balls":11},{"matchId":"981003","innings":1,"wicket":6,"batter1":"NV Ojha","batter2":"EJG Morgan","runs":15,"balls":13},{"matchId":"981003","innings":1,"wicket":7,"batter1":"NV Ojha","batter2":"B Kumar","runs":26,"balls":15},{"matchId":"981003","innings":2,"wicket":1,"batter1":"Q de Kock","batter2":"RR Pant","runs":9,"balls":11},{"matchId":"981003","innings":2,"wicket":2,"batter1":"KK Nair","batter2":"RR Pant","runs":73,"balls":59},{"matchId":"981003","innings":2,"wicket":3,"batter1":"KK Nair","batter2":"JP Duminy","runs":35,"balls":27},{"matchId":"981003","innings":2,"wicket":4,"batter1":"KK Nair","batter2":"CR Brathwaite","runs":26,"balls":13},{"matchId":"981003","innings":2,"wicket":5,"batter1":"KK Nair","batter2":"SV Samson","runs":18,"balls":10},{"matchId":"981005","innings":1,"wicket":1,"batter1":"HM Amla","batter2":"M Vijay","runs":60,"balls":45},{"matchId":"981005","innings":1,"wicket":2,"batter1":"WP Saha","batter2":"M Vijay","runs":5,"balls":6},{"matchId":"981005","innings":1,"wicket":3,"batter1":"Gurkeerat Singh","batter2":"M Vijay","runs":58,"balls":43},{"matchId":"981005","innings":1,"wicket":4,"batter1":"Gurkeerat Singh","batter2":"DA Miller","runs":27,"balls":11},{"matchId":"981005","innings":1,"wicket":5,"batter1":"DA Miller","batter2":"DA Miller","runs":4,"balls":2},{"matchId":"981005","innings":1,"wicket":6,"batter1":"AR Patel","batter2":"DA Miller","runs":6,"balls":7},{"matchId":"981005","innings":1,"wicket":7,"batter1":"AR Patel","batter2":"R Dhawan","runs":0,"balls":1},{"matchId":"981005","innings":1,"wicket":8,"batter1":"R Dhawan","batter2":"R Dhawan","runs":12,"balls":5},{"matchId":"981005","innings":2,"wicket":1,"batter1":"AM Rahane","batter2":"UT Khawaja","runs":35,"balls":28},{"matchId":"981005","innings":2,"wicket":2,"batter1":"GJ Bailey","batter2":"UT Khawaja","runs":12,"balls":14},{"matchId":"981005","innings":2,"wicket":3,"batter1":"UT Khawaja","batter2":"UT Khawaja","runs":31,"balls":26},{"matchId":"981005","innings":2,"wicket":4,"batter1":"UT Khawaja","batter2":"MS Dhoni","runs":2,"balls":3},{"matchId":"981005","innings":2,"wicket":5,"batter1":"IK Pathan","batter2":"MS Dhoni","runs":6,"balls":9},{"matchId":"981005","innings":2,"wicket":6,"batter1":"NLTC Perera","batter2":"MS Dhoni","runs":58,"balls":29},{"matchId":"981005","innings":2,"wicket":7,"batter1":"R Ashwin","batter2":"MS Dhoni","runs":29,"balls":11},{"matchId":"981007","innings":1,"wicket":1,"batter1":"RG Sharma","batter2":"MJ Guptill","runs":33,"balls":23},{"matchId":"981007","innings":1,"wicket":2,"batter1":"N Rana","batter2":"MJ Guptill","runs":8,"balls":4},{"matchId":"981007","innings":1,"wicket":3,"batter1":"N Rana","batter2":"KH Pandya","runs":4,"balls":3},{"matchId":"981007","innings":1,"wicket":4,"batter1":"N Rana","batter2":"JC Buttler","runs":75,"balls":54},{"matchId":"981007","innings":1,"wicket":5,"batter1":"N Rana","batter2":"KA Pollard","runs":33,"balls":19},{"matchId":"981007","innings":1,"wicket":6,"batter1":"HH Pandya","batter2":"KA Pollard","runs":7,"balls":5},{"matchId":"981007","innings":1,"wicket":7,"batter1":"HH Pandya","batter2":"Harbhajan Singh","runs":6,"balls":9},{"matchId":"981007","innings":1,"wicket":8,"batter1":"HH Pandya","batter2":"R Vinay Kumar","runs":6,"balls":4},{"matchId":"981007","innings":2,"wicket":1,"batter1":"AJ Finch","batter2":"BB McCullum","runs":0,"balls":2},{"matchId":"981007","innings":2,"wicket":2,"batter1":"SK Raina","batter2":"BB McCullum","runs":96,"balls":54},{"matchId":"981007","innings":2,"wicket":3,"batter1":"SK Raina","batter2":"KD Karthik","runs":15,"balls":10},{"matchId":"981007","innings":2,"wicket":4,"batter1":"SK Raina","batter2":"DR Smith","runs":11,"balls":8},{"matchId":"981007","innings":2,"wicket":5,"batter1":"DR Smith","batter2":"DR Smith","runs":51,"balls":33},{"matchId":"981009","innings":1,"wicket":1,"batter1":"RV Uthappa","batter2":"G Gambhir","runs":33,"balls":22},{"matchId":"981009","innings":1,"wicket":2,"batter1":"G Gambhir","batter2":"G Gambhir","runs":15,"balls":14},{"matchId":"981009","innings":1,"wicket":3,"batter1":"G Gambhir","batter2":"MK Pandey","runs":9,"balls":9},{"matchId":"981009","innings":1,"wicket":4,"batter1":"YK Pathan","batter2":"MK Pandey","runs":87,"balls":49},{"matchId":"981009","innings":1,"wicket":5,"batter1":"YK Pathan","batter2":"JO Holder","runs":9,"balls":6},{"matchId":"981009","innings":1,"wicket":6,"batter1":"YK Pathan","batter2":"Shakib Al Hasan","runs":11,"balls":15},{"matchId":"981009","innings":1,"wicket":7,"batter1":"YK Pathan","batter2":"SA Yadav","runs":7,"balls":5},{"matchId":"981009","innings":2,"wicket":1,"batter1":"S Dhawan","batter2":"DA Warner","runs":28,"balls":21},{"matchId":"981009","innings":2,"wicket":2,"batter1":"S Dhawan","batter2":"NV Ojha","runs":58,"balls":49},{"matchId":"981009","innings":2,"wicket":3,"batter1":"Yuvraj Singh","batter2":"NV Ojha","runs":6,"balls":4},{"matchId":"981009","innings":2,"wicket":4,"batter1":"Yuvraj Singh","batter2":"KS Williamson","runs":18,"balls":14},{"matchId":"981009","innings":2,"wicket":5,"batter1":"KS Williamson","batter2":"KS Williamson","runs":5,"balls":4},{"matchId":"981009","innings":2,"wicket":6,"batter1":"KS Williamson","batter2":"MC Henriques","runs":2,"balls":3},{"matchId":"981009","innings":2,"wicket":7,"batter1":"MC Henriques","batter2":"MC Henriques","runs":19,"balls":14},{"matchId":"981009","innings":2,"wicket":8,"batter1":"KV Sharma","batter2":"MC Henriques","runs":8,"balls":7},{"matchId":"981009","innings":2,"wicket":9,"batter1":"KV Sharma","batter2":"BB Sran","runs":5,"balls":5},{"matchId":"981011","innings":1,"wicket":1,"batter1":"Q de Kock","batter2":"RR Pant","runs":11,"balls":8},{"matchId":"981011","innings":1,"wicket":2,"batter1":"Q de Kock","batter2":"KK Nair","runs":31,"balls":26},{"matchId":"981011","innings":1,"wicket":3,"batter1":"Q de Kock","batter2":"SV Samson","runs":29,"balls":24},{"matchId":"981011","innings":1,"wicket":4,"batter1":"Q de Kock","batter2":"SW Billings","runs":10,"balls":11},{"matchId":"981011","innings":1,"wicket":5,"batter1":"Q de Kock","batter2":"P Negi","runs":15,"balls":19},{"matchId":"981011","innings":1,"wicket":6,"batter1":"Q de Kock","batter2":"CR Brathwaite","runs":2,"balls":3},{"matchId":"981011","innings":1,"wicket":7,"batter1":"Q de Kock","batter2":"CH Morris","runs":9,"balls":7},{"matchId":"981011","innings":1,"wicket":8,"batter1":"CH Morris","batter2":"CH Morris","runs":31,"balls":23},{"matchId":"981011","innings":2,"wicket":1,"batter1":"CH Gayle","batter2":"V Kohli","runs":5,"balls":7},{"matchId":"981011","innings":2,"wicket":2,"batter1":"AB de Villiers","batter2":"V Kohli","runs":12,"balls":9},{"matchId":"981011","innings":2,"wicket":3,"batter1":"KL Rahul","batter2":"V Kohli","runs":66,"balls":45},{"matchId":"981011","innings":2,"wicket":4,"batter1":"SR Watson","batter2":"V Kohli","runs":28,"balls":29},{"matchId":"981011","innings":2,"wicket":5,"batter1":"STR Binny","batter2":"V Kohli","runs":28,"balls":19},{"matchId":"981013","innings":1,"wicket":1,"batter1":"AJ Finch","batter2":"BB McCullum","runs":2,"balls":7},{"matchId":"981013","innings":1,"wicket":2,"batter1":"AJ Finch","batter2":"SK Raina","runs":4,"balls":3},{"matchId":"981013","innings":1,"wicket":3,"batter1":"KD Karthik","batter2":"SK Raina","runs":3,"balls":12},{"matchId":"981013","innings":1,"wicket":4,"batter1":"KD Karthik","batter2":"DR Smith","runs":85,"balls":61},{"matchId":"981013","innings":1,"wicket":5,"batter1":"RA Jadeja","batter2":"DR Smith","runs":13,"balls":12},{"matchId":"981013","innings":1,"wicket":6,"batter1":"DJ Bravo","batter2":"DR Smith","runs":8,"balls":4},{"matchId":"981013","innings":1,"wicket":7,"batter1":"DJ Bravo","batter2":"ER Dwivedi","runs":30,"balls":12},{"matchId":"981013","innings":1,"wicket":8,"batter1":"DJ Bravo","batter2":"P Kumar","runs":0,"balls":1},{"matchId":"981013","innings":1,"wicket":9,"batter1":"P Kumar","batter2":"P Kumar","runs":11,"balls":5},{"matchId":"981013","innings":1,"wicket":10,"batter1":"SB Jakati","batter2":"P Kumar","runs":2,"balls":3},{"matchId":"981013","innings":2,"wicket":1,"batter1":"CH Gayle","batter2":"V Kohli","runs":12,"balls":8},{"matchId":"981013","innings":2,"wicket":2,"batter1":"CH Gayle","batter2":"AB de Villiers","runs":13,"balls":12},{"matchId":"981013","innings":2,"wicket":3,"batter1":"KL Rahul","batter2":"AB de Villiers","runs":0,"balls":1},{"matchId":"981013","innings":2,"wicket":4,"batter1":"SR Watson","batter2":"AB de Villiers","runs":3,"balls":8},{"matchId":"981013","innings":2,"wicket":5,"batter1":"Sachin Baby","batter2":"AB de Villiers","runs":1,"balls":4},{"matchId":"981013","innings":2,"wicket":6,"batter1":"STR Binny","batter2":"AB de Villiers","runs":39,"balls":25},{"matchId":"981013","innings":2,"wicket":7,"batter1":"Iqbal Abdulla","batter2":"AB de Villiers","runs":91,"balls":53},{"matchId":"981015","innings":1,"wicket":1,"batter1":"DA Warner","batter2":"S Dhawan","runs":12,"balls":12},{"matchId":"981015","innings":1,"wicket":2,"batter1":"DA Warner","batter2":"MC Henriques","runs":59,"balls":46},{"matchId":"981015","innings":1,"wicket":3,"batter1":"DA Warner","batter2":"Yuvraj Singh","runs":0,"balls":1},{"matchId":"981015","innings":1,"wicket":4,"batter1":"DJ Hooda","batter2":"Yuvraj Singh","runs":49,"balls":36},{"matchId":"981015","innings":1,"wicket":5,"batter1":"Yuvraj Singh","batter2":"Yuvraj Singh","runs":4,"balls":2},{"matchId":"981015","innings":1,"wicket":6,"batter1":"Yuvraj Singh","batter2":"NV Ojha","runs":21,"balls":14},{"matchId":"981015","innings":1,"wicket":7,"batter1":"B Kumar","batter2":"NV Ojha","runs":2,"balls":2},{"matchId":"981015","innings":1,"wicket":8,"batter1":"B Kumar","batter2":"Bipul Sharma","runs":14,"balls":6},{"matchId":"981015","innings":1,"wicket":9,"batter1":"Bipul Sharma","batter2":"Bipul Sharma","runs":1,"balls":1},{"matchId":"981015","innings":2,"wicket":1,"batter1":"RV Uthappa","batter2":"G Gambhir","runs":15,"balls":11},{"matchId":"981015","innings":2,"wicket":2,"batter1":"C Munro","batter2":"G Gambhir","runs":38,"balls":31},{"matchId":"981015","innings":2,"wicket":3,"batter1":"G Gambhir","batter2":"G Gambhir","runs":10,"balls":13},{"matchId":"981015","innings":2,"wicket":4,"batter1":"MK Pandey","batter2":"G Gambhir","runs":6,"balls":10},{"matchId":"981015","innings":2,"wicket":5,"batter1":"MK Pandey","batter2":"SA Yadav","runs":46,"balls":30},{"matchId":"981015","innings":2,"wicket":6,"batter1":"MK Pandey","batter2":"R Sathish","runs":10,"balls":9},{"matchId":"981015","innings":2,"wicket":7,"batter1":"R Sathish","batter2":"R Sathish","runs":14,"balls":12},{"matchId":"981015","innings":2,"wicket":8,"batter1":"SP Narine","batter2":"R Sathish","runs":1,"balls":3},{"matchId":"981015","innings":2,"wicket":9,"batter1":"SP Narine","batter2":"M Morkel","runs":0,"balls":1},{"matchId":"981017","innings":1,"wicket":1,"batter1":"ER Dwivedi","batter2":"BB McCullum","runs":7,"balls":6},{"matchId":"981017","innings":1,"wicket":2,"batter1":"BB McCullum","batter2":"BB McCullum","runs":12,"balls":14},{"matchId":"981017","innings":1,"wicket":3,"batter1":"BB McCullum","batter2":"KD Karthik","runs":44,"balls":33},{"matchId":"981017","innings":1,"wicket":4,"batter1":"BB McCullum","batter2":"AJ Finch","runs":18,"balls":19},{"matchId":"981017","innings":1,"wicket":5,"batter1":"DR Smith","batter2":"AJ Finch","runs":2,"balls":4},{"matchId":"981017","innings":1,"wicket":6,"batter1":"AJ Finch","batter2":"AJ Finch","runs":51,"balls":29},{"matchId":"981017","innings":1,"wicket":7,"batter1":"DJ Bravo","batter2":"AJ Finch","runs":24,"balls":12},{"matchId":"981017","innings":1,"wicket":8,"batter1":"DS Kulkarni","batter2":"AJ Finch","runs":4,"balls":3},{"matchId":"981017","innings":2,"wicket":1,"batter1":"DA Warner","batter2":"S Dhawan","runs":6,"balls":7},{"matchId":"981017","innings":2,"wicket":2,"batter1":"DA Warner","batter2":"MC Henriques","runs":27,"balls":18},{"matchId":"981017","innings":2,"wicket":3,"batter1":"DA Warner","batter2":"Yuvraj Singh","runs":28,"balls":25},{"matchId":"981017","innings":2,"wicket":4,"batter1":"DA Warner","batter2":"DJ Hooda","runs":14,"balls":17},{"matchId":"981017","innings":2,"wicket":5,"batter1":"DA Warner","batter2":"BCJ Cutting","runs":9,"balls":8},{"matchId":"981017","innings":2,"wicket":6,"batter1":"DA Warner","batter2":"NV Ojha","runs":33,"balls":20},{"matchId":"981017","innings":2,"wicket":7,"batter1":"DA Warner","batter2":"Bipul Sharma","runs":46,"balls":21},{"matchId":"981019","innings":1,"wicket":1,"batter1":"DA Warner","batter2":"S Dhawan","runs":63,"balls":40},{"matchId":"981019","innings":1,"wicket":2,"batter1":"DA Warner","batter2":"MC Henriques","runs":34,"balls":19},{"matchId":"981019","innings":1,"wicket":3,"batter1":"DA Warner","batter2":"Yuvraj Singh","runs":28,"balls":22},{"matchId":"981019","innings":1,"wicket":4,"batter1":"DJ Hooda","batter2":"Yuvraj Singh","runs":22,"balls":15},{"matchId":"981019","innings":1,"wicket":5,"batter1":"Yuvraj Singh","batter2":"Yuvraj Singh","runs":1,"balls":1},{"matchId":"981019","innings":1,"wicket":6,"batter1":"NV Ojha","batter2":"Yuvraj Singh","runs":10,"balls":6},{"matchId":"981019","innings":1,"wicket":7,"batter1":"BCJ Cutting","batter2":"Yuvraj Singh","runs":16,"balls":9},{"matchId":"981019","innings":1,"wicket":8,"batter1":"BCJ Cutting","batter2":"B Kumar","runs":34,"balls":8},{"matchId":"981019","innings":2,"wicket":1,"batter1":"CH Gayle","batter2":"V Kohli","runs":114,"balls":63},{"matchId":"981019","innings":2,"wicket":2,"batter1":"V Kohli","batter2":"V Kohli","runs":26,"balls":14},{"matchId":"981019","innings":2,"wicket":3,"batter1":"KL Rahul","batter2":"V Kohli","runs":8,"balls":6},{"matchId":"981019","innings":2,"wicket":4,"batter1":"KL Rahul","batter2":"SR Watson","runs":12,"balls":10},{"matchId":"981019","innings":2,"wicket":5,"batter1":"Sachin Baby","batter2":"SR Watson","runs":4,"balls":6},{"matchId":"981019","innings":2,"wicket":6,"batter1":"Sachin Baby","batter2":"STR Binny","runs":16,"balls":10},{"matchId":"981019","innings":2,"wicket":7,"batter1":"Sachin Baby","batter2":"CJ Jordan","runs":14,"balls":8},{"matchId":"981019","innings":2,"wicket":8,"batter1":"Sachin Baby","batter2":"Iqbal Abdulla","runs":6,"balls":3}]